[
{"prod_url": "https://www.bestdenki.com.sg/1105059-karcher-steam-sanitiser-sc2-upright-easyfix.html", "site_url": "https://www.bestdenki.com.sg/home-appliances/vacuum.html", "category": "Vacuum"},
{"prod_url": "https://www.bestdenki.com.sg/1105142-lg-rechargeable-vac-a9-lite.html", "site_url": "https://www.bestdenki.com.sg/home-appliances/vacuum.html", "category": "Vacuum"},
{"prod_url": "https://www.bestdenki.com.sg/1105143-karcher-high-pressure-cleaner-k5-power-control.html", "site_url": "https://www.bestdenki.com.sg/home-appliances/vacuum.html", "category": "Vacuum"},
{"prod_url": "https://www.bestdenki.com.sg/1105144-electrolux-03l-rechargeable-vac-2-in-1-wq61-10gg.html", "site_url": "https://www.bestdenki.com.sg/home-appliances/vacuum.html", "category": "Vacuum"},
{"prod_url": "https://www.bestdenki.com.sg/1105148-electrolux-0-4l-rechargeable-vac-2-in-1-efp91814wh.html", "site_url": "https://www.bestdenki.com.sg/home-appliances/vacuum.html", "category": "Vacuum"},
{"prod_url": "https://www.bestdenki.com.sg/1105153-shark-cordfree-handheld-vacuum-wv203-grey.html", "site_url": "https://www.bestdenki.com.sg/home-appliances/vacuum.html", "category": "Vacuum"},
{"prod_url": "https://www.bestdenki.com.sg/1105154-shark-cordfree-handheld-vacuum-wv204-black.html", "site_url": "https://www.bestdenki.com.sg/home-appliances/vacuum.html", "category": "Vacuum"},
{"prod_url": "https://www.bestdenki.com.sg/1105155-shark-cordfree-handheld-vacuum-wv205-blue.html", "site_url": "https://www.bestdenki.com.sg/home-appliances/vacuum.html", "category": "Vacuum"},
{"prod_url": "https://www.bestdenki.com.sg/1105156-shark-cordfree-handheld-vacuum-wv206-pink.html", "site_url": "https://www.bestdenki.com.sg/home-appliances/vacuum.html", "category": "Vacuum"},
{"prod_url": "https://www.bestdenki.com.sg/1105062-philips-bagless-vacuum-xb2023-61.html", "site_url": "https://www.bestdenki.com.sg/home-appliances/vacuum.html", "category": "Vacuum"},
{"prod_url": "https://www.bestdenki.com.sg/1103275-miele-normal-vacuum-complete-c3-marine-blue.html", "site_url": "https://www.bestdenki.com.sg/home-appliances/vacuum.html", "category": "Vacuum"},
{"prod_url": "https://www.bestdenki.com.sg/1103284-karcher-high-pressure-cleaner-k2-compact.html", "site_url": "https://www.bestdenki.com.sg/home-appliances/vacuum.html", "category": "Vacuum"},
{"prod_url": "https://www.bestdenki.com.sg/1103484-karcher-bagless-vacuum-vc3-premium-plus-white.html", "site_url": "https://www.bestdenki.com.sg/home-appliances/vacuum.html?p=2", "category": "Vacuum"},
{"prod_url": "https://www.bestdenki.com.sg/1103838-philips-bagless-vacuum-fc9352-61.html", "site_url": "https://www.bestdenki.com.sg/home-appliances/vacuum.html?p=2", "category": "Vacuum"},
{"prod_url": "https://www.bestdenki.com.sg/1104024-miele-bagless-vacuum-skcr3-white.html", "site_url": "https://www.bestdenki.com.sg/home-appliances/vacuum.html?p=2", "category": "Vacuum"},
{"prod_url": "https://www.bestdenki.com.sg/1104025-miele-bagless-vacuum-skrr3-red.html", "site_url": "https://www.bestdenki.com.sg/home-appliances/vacuum.html?p=2", "category": "Vacuum"},
{"prod_url": "https://www.bestdenki.com.sg/1102190-rowenta-dust-bag-zr0039.html", "site_url": "https://www.bestdenki.com.sg/home-appliances/vacuum.html?p=2", "category": "Vacuum"},
{"prod_url": "https://www.bestdenki.com.sg/1102228-rowenta-dust-bag-wb4847-endura-wonderbag.html", "site_url": "https://www.bestdenki.com.sg/home-appliances/vacuum.html?p=2", "category": "Vacuum"},
{"prod_url": "https://www.bestdenki.com.sg/1102591-karcher-normal-vacuum-se6100.html", "site_url": "https://www.bestdenki.com.sg/home-appliances/vacuum.html?p=2", "category": "Vacuum"},
{"prod_url": "https://www.bestdenki.com.sg/1103008-karcher-normal-vacuum-ds6000.html", "site_url": "https://www.bestdenki.com.sg/home-appliances/vacuum.html?p=2", "category": "Vacuum"},
{"prod_url": "https://www.bestdenki.com.sg/1103271-miele-normal-vacuum-compact-c2-marine-blue.html", "site_url": "https://www.bestdenki.com.sg/home-appliances/vacuum.html?p=2", "category": "Vacuum"},
{"prod_url": "https://www.bestdenki.com.sg/1103281-karcher-steam-sanitiser-sv7.html", "site_url": "https://www.bestdenki.com.sg/home-appliances/vacuum.html?p=2", "category": "Vacuum"},
{"prod_url": "https://www.bestdenki.com.sg/1103470-karcher-canister-type-vac-wd3.html", "site_url": "https://www.bestdenki.com.sg/home-appliances/vacuum.html?p=2", "category": "Vacuum"},
{"prod_url": "https://www.bestdenki.com.sg/1103576-tefal-hepa-filter-zr0057.html", "site_url": "https://www.bestdenki.com.sg/home-appliances/vacuum.html?p=2", "category": "Vacuum"},
{"prod_url": "https://www.bestdenki.com.sg/1103579-tefal-washable-bag-zr9028.html", "site_url": "https://www.bestdenki.com.sg/home-appliances/vacuum.html?p=3", "category": "Vacuum"},
{"prod_url": "https://www.bestdenki.com.sg/1103716-tefal-hygiene-plus-bag-zr2005.html", "site_url": "https://www.bestdenki.com.sg/home-appliances/vacuum.html?p=3", "category": "Vacuum"},
{"prod_url": "https://www.bestdenki.com.sg/1103717-tefal-anti-odour-bag-zr2007.html", "site_url": "https://www.bestdenki.com.sg/home-appliances/vacuum.html?p=3", "category": "Vacuum"},
{"prod_url": "https://www.bestdenki.com.sg/1103820-tefal-bagless-vacuum-tw3233.html", "site_url": "https://www.bestdenki.com.sg/home-appliances/vacuum.html?p=3", "category": "Vacuum"},
{"prod_url": "https://www.bestdenki.com.sg/1103839-philips-bagless-vacuum-fc9350-61.html", "site_url": "https://www.bestdenki.com.sg/home-appliances/vacuum.html?p=3", "category": "Vacuum"},
{"prod_url": "https://www.bestdenki.com.sg/1103844-electrolux-canister-type-vac-z823.html", "site_url": "https://www.bestdenki.com.sg/home-appliances/vacuum.html?p=3", "category": "Vacuum"},
{"prod_url": "https://www.bestdenki.com.sg/1103856-electrolux-normal-vacuum-z1220.html", "site_url": "https://www.bestdenki.com.sg/home-appliances/vacuum.html?p=3", "category": "Vacuum"},
{"prod_url": "https://www.bestdenki.com.sg/1104008-electrolux-bagless-vacuum-z1231.html", "site_url": "https://www.bestdenki.com.sg/home-appliances/vacuum.html?p=3", "category": "Vacuum"},
{"prod_url": "https://www.bestdenki.com.sg/1104009-karcher-steam-cleaner-sc2-deluxe.html", "site_url": "https://www.bestdenki.com.sg/home-appliances/vacuum.html?p=3", "category": "Vacuum"},
{"prod_url": "https://www.bestdenki.com.sg/1104647-miele-normal-vacuum-c3-allergy-powerline-blue.html", "site_url": "https://www.bestdenki.com.sg/home-appliances/vacuum.html?p=3", "category": "Vacuum"},
{"prod_url": "https://www.bestdenki.com.sg/1104718-electrolux-bagless-vacuum-ec41-6cr.html", "site_url": "https://www.bestdenki.com.sg/home-appliances/vacuum.html?p=3", "category": "Vacuum"},
{"prod_url": "https://www.bestdenki.com.sg/1104886-electrolux-robotic-vacuum-pi92-6sgm.html", "site_url": "https://www.bestdenki.com.sg/home-appliances/vacuum.html?p=3", "category": "Vacuum"},
{"prod_url": "https://www.bestdenki.com.sg/1104928-tefal-normal-vacuum-tw2947.html", "site_url": "https://www.bestdenki.com.sg/home-appliances/vacuum.html?p=4", "category": "Vacuum"},
{"prod_url": "https://www.bestdenki.com.sg/1104950-karcher-rechargeable-vac-vc4s.html", "site_url": "https://www.bestdenki.com.sg/home-appliances/vacuum.html?p=4", "category": "Vacuum"},
{"prod_url": "https://www.bestdenki.com.sg/1105022-tefal-bagless-vacuum-tw4871.html", "site_url": "https://www.bestdenki.com.sg/home-appliances/vacuum.html?p=4", "category": "Vacuum"},
{"prod_url": "https://www.bestdenki.com.sg/1105032-miele-normal-vacuum-complete-c3-powerline-grey.html", "site_url": "https://www.bestdenki.com.sg/home-appliances/vacuum.html?p=4", "category": "Vacuum"},
{"prod_url": "https://www.bestdenki.com.sg/1105034-tefal-bagless-vacuum-tw7253-exclusive.html", "site_url": "https://www.bestdenki.com.sg/home-appliances/vacuum.html?p=4", "category": "Vacuum"},
{"prod_url": "https://www.bestdenki.com.sg/1105051-tefal-bagless-vacuum-tw7260.html", "site_url": "https://www.bestdenki.com.sg/home-appliances/vacuum.html?p=4", "category": "Vacuum"},
{"prod_url": "https://www.bestdenki.com.sg/1105052-tefal-bagless-vacuum-tw7689.html", "site_url": "https://www.bestdenki.com.sg/home-appliances/vacuum.html?p=4", "category": "Vacuum"},
{"prod_url": "https://www.bestdenki.com.sg/1105053-lg-rechargeable-vac-a9k-ultra.html", "site_url": "https://www.bestdenki.com.sg/home-appliances/vacuum.html?p=4", "category": "Vacuum"},
{"prod_url": "https://www.bestdenki.com.sg/1105054-lg-rechargeable-vac-a9k-pro.html", "site_url": "https://www.bestdenki.com.sg/home-appliances/vacuum.html?p=4", "category": "Vacuum"},
{"prod_url": "https://www.bestdenki.com.sg/1105055-lg-rechargeable-vac-a9k-core.html", "site_url": "https://www.bestdenki.com.sg/home-appliances/vacuum.html?p=4", "category": "Vacuum"},
{"prod_url": "https://www.bestdenki.com.sg/1105058-karcher-handheld-vacuum-vch2.html", "site_url": "https://www.bestdenki.com.sg/home-appliances/vacuum.html?p=4", "category": "Vacuum"},
{"prod_url": "https://www.bestdenki.com.sg/1105065-samsung-robotic-vacuum-vr30t85513w-sp.html", "site_url": "https://www.bestdenki.com.sg/home-appliances/vacuum.html?p=4", "category": "Vacuum"},
{"prod_url": "https://www.bestdenki.com.sg/1105066-samsung-robotic-vacuum-vr30t80313w-sp.html", "site_url": "https://www.bestdenki.com.sg/home-appliances/vacuum.html?p=5", "category": "Vacuum"},
{"prod_url": "https://www.bestdenki.com.sg/1105115-electrolux-rechargeable-vac-pq92-3sbwf.html", "site_url": "https://www.bestdenki.com.sg/home-appliances/vacuum.html?p=5", "category": "Vacuum"},
{"prod_url": "https://www.bestdenki.com.sg/1105174-lg-rechargeable-vac-a9t-ultra.html", "site_url": "https://www.bestdenki.com.sg/home-appliances/vacuum.html?p=5", "category": "Vacuum"},
{"prod_url": "https://www.bestdenki.com.sg/1105177-shark-wandvac-system-ws632gysm-grey.html", "site_url": "https://www.bestdenki.com.sg/home-appliances/vacuum.html?p=5", "category": "Vacuum"},
{"prod_url": "https://www.bestdenki.com.sg/1105178-shark-wandvac-system-ws632rgsm-rose-gold.html", "site_url": "https://www.bestdenki.com.sg/home-appliances/vacuum.html?p=5", "category": "Vacuum"},
{"prod_url": "https://www.bestdenki.com.sg/1105424-dyson-rechargeable-vac-v12s-submarine-620h.html", "site_url": "https://www.bestdenki.com.sg/home-appliances/vacuum.html?p=5", "category": "Vacuum"},
{"prod_url": "https://www.bestdenki.com.sg/1105435-dyson-rechargeable-vac-sv23-gen5-detect.html", "site_url": "https://www.bestdenki.com.sg/home-appliances/vacuum.html?p=5", "category": "Vacuum"},
{"prod_url": "https://www.bestdenki.com.sg/1105436-lg-rechargeable-vac-a9t-steam.html", "site_url": "https://www.bestdenki.com.sg/home-appliances/vacuum.html?p=5", "category": "Vacuum"},
{"prod_url": "https://www.bestdenki.com.sg/1105437-lg-rechargeable-vac-a9t-auto.html", "site_url": "https://www.bestdenki.com.sg/home-appliances/vacuum.html?p=5", "category": "Vacuum"},
{"prod_url": "https://www.bestdenki.com.sg/1105471-electrolux-rechargeable-vac-efw71711.html", "site_url": "https://www.bestdenki.com.sg/home-appliances/vacuum.html?p=5", "category": "Vacuum"},
{"prod_url": "https://www.bestdenki.com.sg/1105473-samsung-rechargeable-vac-vs28c976fqg-sp.html", "site_url": "https://www.bestdenki.com.sg/home-appliances/vacuum.html?p=5", "category": "Vacuum"},
{"prod_url": "https://www.bestdenki.com.sg/1105474-samsung-rechargeable-vac-vs28c979fqk-sp.html", "site_url": "https://www.bestdenki.com.sg/home-appliances/vacuum.html?p=5", "category": "Vacuum"},
{"prod_url": "https://www.bestdenki.com.sg/1105475-ecovacs-robotic-vacuum-deebot-n10.html", "site_url": "https://www.bestdenki.com.sg/home-appliances/vacuum.html?p=6", "category": "Vacuum"},
{"prod_url": "https://www.bestdenki.com.sg/1105476-ecovacs-robotic-vacuum-deebot-t10.html", "site_url": "https://www.bestdenki.com.sg/home-appliances/vacuum.html?p=6", "category": "Vacuum"},
{"prod_url": "https://www.bestdenki.com.sg/1105477-ecovacs-robotic-vacuum-deebot-t10-omni.html", "site_url": "https://www.bestdenki.com.sg/home-appliances/vacuum.html?p=6", "category": "Vacuum"},
{"prod_url": "https://www.bestdenki.com.sg/1105478-ecovacs-robotic-vacuum-deebot-t20-omni.html", "site_url": "https://www.bestdenki.com.sg/home-appliances/vacuum.html?p=6", "category": "Vacuum"},
{"prod_url": "https://www.bestdenki.com.sg/1105481-ecovacs-robotic-vacuum-deebot-x2-omni-black.html", "site_url": "https://www.bestdenki.com.sg/home-appliances/vacuum.html?p=6", "category": "Vacuum"},
{"prod_url": "https://www.bestdenki.com.sg/1105443-karcher-rechargeable-vac-vcs3.html", "site_url": "https://www.bestdenki.com.sg/home-appliances/vacuum.html?p=6", "category": "Vacuum"},
{"prod_url": "https://www.bestdenki.com.sg/1105447-dyson-rechargeable-vac-sv46v12-fluffy.html", "site_url": "https://www.bestdenki.com.sg/home-appliances/vacuum.html?p=6", "category": "Vacuum"},
{"prod_url": "https://www.bestdenki.com.sg/1105448-dyson-rechargeable-vac-sv46v12-absolute.html", "site_url": "https://www.bestdenki.com.sg/home-appliances/vacuum.html?p=6", "category": "Vacuum"},
{"prod_url": "https://www.bestdenki.com.sg/1105451-karcher-steam-sanitiser-sc4-deluxe-premium.html", "site_url": "https://www.bestdenki.com.sg/home-appliances/vacuum.html?p=6", "category": "Vacuum"},
{"prod_url": "https://www.bestdenki.com.sg/1105462-dyson-rechargeable-vac-sv18-dslim-fluffy-origin.html", "site_url": "https://www.bestdenki.com.sg/home-appliances/vacuum.html?p=6", "category": "Vacuum"},
{"prod_url": "https://www.bestdenki.com.sg/1105463-philips-rechargeable-vac-xc7055-01.html", "site_url": "https://www.bestdenki.com.sg/home-appliances/vacuum.html?p=6", "category": "Vacuum"},
{"prod_url": "https://www.bestdenki.com.sg/1105464-philips-rechargeable-vac-xw7110-02.html", "site_url": "https://www.bestdenki.com.sg/home-appliances/vacuum.html?p=6", "category": "Vacuum"},
{"prod_url": "https://www.bestdenki.com.sg/1105394-tefal-rechargeable-vac-gf3039.html", "site_url": "https://www.bestdenki.com.sg/home-appliances/vacuum.html?p=7", "category": "Vacuum"},
{"prod_url": "https://www.bestdenki.com.sg/1105398-europace-rechargeable-vac-ehva5320.html", "site_url": "https://www.bestdenki.com.sg/home-appliances/vacuum.html?p=7", "category": "Vacuum"},
{"prod_url": "https://www.bestdenki.com.sg/1105417-philips-rechargeable-vac-xw9383-02.html", "site_url": "https://www.bestdenki.com.sg/home-appliances/vacuum.html?p=7", "category": "Vacuum"},
{"prod_url": "https://www.bestdenki.com.sg/1105419-tefal-rechargeable-vac-ty1238.html", "site_url": "https://www.bestdenki.com.sg/home-appliances/vacuum.html?p=7", "category": "Vacuum"},
{"prod_url": "https://www.bestdenki.com.sg/1105487-tefal-handheld-vacuum-ty20c7.html", "site_url": "https://www.bestdenki.com.sg/home-appliances/vacuum.html?p=7", "category": "Vacuum"},
{"prod_url": "https://www.bestdenki.com.sg/1105495-dreame-robotic-vacuum-l10-prime.html", "site_url": "https://www.bestdenki.com.sg/home-appliances/vacuum.html?p=7", "category": "Vacuum"},
{"prod_url": "https://www.bestdenki.com.sg/1105497-dreame-rechargeable-vac-h12-pro.html", "site_url": "https://www.bestdenki.com.sg/home-appliances/vacuum.html?p=7", "category": "Vacuum"},
{"prod_url": "https://www.bestdenki.com.sg/1105498-dreame-robotic-vacuum-l10s-ultra-se.html", "site_url": "https://www.bestdenki.com.sg/home-appliances/vacuum.html?p=7", "category": "Vacuum"},
{"prod_url": "https://www.bestdenki.com.sg/1105499-dreame-robotic-vacuum-l20-ultra.html", "site_url": "https://www.bestdenki.com.sg/home-appliances/vacuum.html?p=7", "category": "Vacuum"},
{"prod_url": "https://www.bestdenki.com.sg/1105500-dreame-rechargeable-vac-r10.html", "site_url": "https://www.bestdenki.com.sg/home-appliances/vacuum.html?p=7", "category": "Vacuum"},
{"prod_url": "https://www.bestdenki.com.sg/1105501-dreame-rechargeable-vac-r20.html", "site_url": "https://www.bestdenki.com.sg/home-appliances/vacuum.html?p=7", "category": "Vacuum"},
{"prod_url": "https://www.bestdenki.com.sg/1105506-samsung-rechargeable-vac-jet-75e-multi-vs20b75aer1-sp.html", "site_url": "https://www.bestdenki.com.sg/home-appliances/vacuum.html?p=7", "category": "Vacuum"},
{"prod_url": "https://www.bestdenki.com.sg/1105507-samsung-rechargeable-vac-jet-85-premium-vs20c852ftb-sp.html", "site_url": "https://www.bestdenki.com.sg/home-appliances/vacuum.html?p=8", "category": "Vacuum"},
{"prod_url": "https://www.bestdenki.com.sg/1105508-dyson-rechargeable-vac-sv49v12-origin.html", "site_url": "https://www.bestdenki.com.sg/home-appliances/vacuum.html?p=8", "category": "Vacuum"},
{"prod_url": "https://www.bestdenki.com.sg/1105522-philips-robotic-vacuum-xu6500-82.html", "site_url": "https://www.bestdenki.com.sg/home-appliances/vacuum.html?p=8", "category": "Vacuum"},
{"prod_url": "https://www.bestdenki.com.sg/1105526-sharp-rechargeable-vac-ecsa95s-r.html", "site_url": "https://www.bestdenki.com.sg/home-appliances/vacuum.html?p=8", "category": "Vacuum"},
{"prod_url": "https://www.bestdenki.com.sg/1105537-shark-rechargeable-vac-iw3241sm.html", "site_url": "https://www.bestdenki.com.sg/home-appliances/vacuum.html?p=8", "category": "Vacuum"},
{"prod_url": "https://www.bestdenki.com.sg/1105538-shark-rechargeable-vac-iw2241sm.html", "site_url": "https://www.bestdenki.com.sg/home-appliances/vacuum.html?p=8", "category": "Vacuum"},
{"prod_url": "https://www.bestdenki.com.sg/1105539-shark-rechargeable-vac-cs851smmvae.html", "site_url": "https://www.bestdenki.com.sg/home-appliances/vacuum.html?p=8", "category": "Vacuum"},
{"prod_url": "https://www.bestdenki.com.sg/1105540-shark-rechargeable-vac-cs851smbr.html", "site_url": "https://www.bestdenki.com.sg/home-appliances/vacuum.html?p=8", "category": "Vacuum"},
{"prod_url": "https://www.bestdenki.com.sg/0403653-vago-portable-vacuum-tvd2-white.html", "site_url": "https://www.bestdenki.com.sg/home-appliances/vacuum.html?p=8", "category": "Vacuum"},
{"prod_url": "https://www.bestdenki.com.sg/0403654-vago-portable-vacuum-tvd2-black.html", "site_url": "https://www.bestdenki.com.sg/home-appliances/vacuum.html?p=8", "category": "Vacuum"},
{"prod_url": "https://www.bestdenki.com.sg/0403655-vago-portable-vacuum-tvd2-pink.html", "site_url": "https://www.bestdenki.com.sg/home-appliances/vacuum.html?p=8", "category": "Vacuum"},
{"prod_url": "https://www.bestdenki.com.sg/0403656-vago-portable-vacuum-tvd2-purple.html", "site_url": "https://www.bestdenki.com.sg/home-appliances/vacuum.html?p=8", "category": "Vacuum"},
{"prod_url": "https://www.bestdenki.com.sg/1105362-shark-steam-and-scrub-mop-s7001.html", "site_url": "https://www.bestdenki.com.sg/home-appliances/vacuum.html?p=9", "category": "Vacuum"},
{"prod_url": "https://www.bestdenki.com.sg/1105364-tp-link-robotic-vacuum-tapo-rv10.html", "site_url": "https://www.bestdenki.com.sg/home-appliances/vacuum.html?p=9", "category": "Vacuum"},
{"prod_url": "https://www.bestdenki.com.sg/1105365-tp-link-robotic-vacuum-tapo-rv10-plus.html", "site_url": "https://www.bestdenki.com.sg/home-appliances/vacuum.html?p=9", "category": "Vacuum"},
{"prod_url": "https://www.bestdenki.com.sg/1105366-tp-link-robotic-vacuum-tapo-rv30-plus.html", "site_url": "https://www.bestdenki.com.sg/home-appliances/vacuum.html?p=9", "category": "Vacuum"},
{"prod_url": "https://www.bestdenki.com.sg/1105218-bosch-rechargeable-vac-bbh3zoo28.html", "site_url": "https://www.bestdenki.com.sg/home-appliances/vacuum.html?p=9", "category": "Vacuum"},
{"prod_url": "https://www.bestdenki.com.sg/1105223-tefal-rechargeable-vac-ty9890.html", "site_url": "https://www.bestdenki.com.sg/home-appliances/vacuum.html?p=9", "category": "Vacuum"},
{"prod_url": "https://www.bestdenki.com.sg/1105225-karcher-castylernister-type-vac-wd5s.html", "site_url": "https://www.bestdenki.com.sg/home-appliances/vacuum.html?p=9", "category": "Vacuum"},
{"prod_url": "https://www.bestdenki.com.sg/1105227-karcher-high-pressure-cleaner-k-mini.html", "site_url": "https://www.bestdenki.com.sg/home-appliances/vacuum.html?p=9", "category": "Vacuum"},
{"prod_url": "https://www.bestdenki.com.sg/1105389-electrolux-rechargeable-vac-efp71512.html", "site_url": "https://www.bestdenki.com.sg/home-appliances/vacuum.html?p=9", "category": "Vacuum"},
{"prod_url": "https://www.bestdenki.com.sg/1105390-electrolux-rechargeable-vac-efp71525.html", "site_url": "https://www.bestdenki.com.sg/home-appliances/vacuum.html?p=9", "category": "Vacuum"},
{"prod_url": "https://www.bestdenki.com.sg/1105286-tefal-rechargeable-vac-ty6837.html", "site_url": "https://www.bestdenki.com.sg/home-appliances/vacuum.html?p=9", "category": "Vacuum"},
{"prod_url": "https://www.bestdenki.com.sg/1105222-shark-steam-mop-s1000.html", "site_url": "https://www.bestdenki.com.sg/home-appliances/vacuum.html?p=9", "category": "Vacuum"},
{"prod_url": "https://www.bestdenki.com.sg/1105295-dyson-rechargeable-vac-sv10kv8-slim-fluffy-red.html", "site_url": "https://www.bestdenki.com.sg/home-appliances/vacuum.html?p=10", "category": "Vacuum"},
{"prod_url": "https://www.bestdenki.com.sg/1105246-electrolux-bagless-vacuum-efc71622sw.html", "site_url": "https://www.bestdenki.com.sg/home-appliances/vacuum.html?p=10", "category": "Vacuum"},
{"prod_url": "https://www.bestdenki.com.sg/1103269-miele-normal-vacuum-classic-c1-lotus-white.html", "site_url": "https://www.bestdenki.com.sg/home-appliances/vacuum.html?p=10", "category": "Vacuum"},
{"prod_url": "https://www.bestdenki.com.sg/1105317-electrolux-rechargeable-vac-efp31212.html", "site_url": "https://www.bestdenki.com.sg/home-appliances/vacuum.html?p=10", "category": "Vacuum"},
{"prod_url": "https://www.bestdenki.com.sg/1105327-karcher-handheld-vacuum-vcs5.html", "site_url": "https://www.bestdenki.com.sg/home-appliances/vacuum.html?p=10", "category": "Vacuum"},
{"prod_url": "https://www.bestdenki.com.sg/1105330-electrolux-dust-bag-e200b-bag.html", "site_url": "https://www.bestdenki.com.sg/home-appliances/vacuum.html?p=10", "category": "Vacuum"},
{"prod_url": "https://www.bestdenki.com.sg/1105260-miele-robotic-vacuum-scout-rx3.html", "site_url": "https://www.bestdenki.com.sg/home-appliances/vacuum.html?p=10", "category": "Vacuum"},
{"prod_url": "https://www.bestdenki.com.sg/1100322-philips-dust-bag-fc8021.html", "site_url": "https://www.bestdenki.com.sg/home-appliances/vacuum.html?p=10", "category": "Vacuum"},
{"prod_url": "https://www.bestdenki.com.sg/1101118-karcher-dust-bag-filter-bag-a2204.html", "site_url": "https://www.bestdenki.com.sg/home-appliances/vacuum.html?p=10", "category": "Vacuum"},
{"prod_url": "https://www.bestdenki.com.sg/1101500-hitachi-dust-bag-dustbag-cvsh20v.html", "site_url": "https://www.bestdenki.com.sg/home-appliances/vacuum.html?p=10", "category": "Vacuum"},
{"prod_url": "https://www.bestdenki.com.sg/1102998-rowenta-dust-bag-wb305120-compacteo-ergo.html", "site_url": "https://www.bestdenki.com.sg/home-appliances/vacuum.html?p=10", "category": "Vacuum"},
{"prod_url": "https://www.bestdenki.com.sg/1103587-karcher-dust-bag-filter-bag-vc2.html", "site_url": "https://www.bestdenki.com.sg/home-appliances/vacuum.html?p=10", "category": "Vacuum"},
{"prod_url": "https://www.bestdenki.com.sg/1105271-tefal-rechargeable-vac-ty9670.html", "site_url": "https://www.bestdenki.com.sg/home-appliances/vacuum.html?p=11", "category": "Vacuum"},
{"prod_url": "https://www.bestdenki.com.sg/1105273-miele-bagless-vacuum-boost-cx1-parquet.html", "site_url": "https://www.bestdenki.com.sg/home-appliances/vacuum.html?p=11", "category": "Vacuum"},
{"prod_url": "https://www.bestdenki.com.sg/1105274-miele-bagless-vacuum-boost-cx1.html", "site_url": "https://www.bestdenki.com.sg/home-appliances/vacuum.html?p=11", "category": "Vacuum"},
{"prod_url": "https://www.bestdenki.com.sg/1105275-miele-bagless-vacuum-boost-cx1-cat-dog.html", "site_url": "https://www.bestdenki.com.sg/home-appliances/vacuum.html?p=11", "category": "Vacuum"},
{"prod_url": "https://www.bestdenki.com.sg/1105276-yeedi-robotic-vacuum-k650.html", "site_url": "https://www.bestdenki.com.sg/home-appliances/vacuum.html?p=11", "category": "Vacuum"},
{"prod_url": "https://www.bestdenki.com.sg/1105277-yeedi-robotic-vacuum-k950.html", "site_url": "https://www.bestdenki.com.sg/home-appliances/vacuum.html?p=11", "category": "Vacuum"},
{"prod_url": "https://www.bestdenki.com.sg/1101771-rowenta-dust-bag-wb4061-wonderbag.html", "site_url": "https://www.bestdenki.com.sg/home-appliances/vacuum.html?p=11", "category": "Vacuum"},
{"prod_url": "https://www.bestdenki.com.sg/1104626-tefal-dust-bag-zr0060.html", "site_url": "https://www.bestdenki.com.sg/home-appliances/vacuum.html?p=11", "category": "Vacuum"},
{"prod_url": "https://www.bestdenki.com.sg/1104627-tefal-dust-bag-zr0059.html", "site_url": "https://www.bestdenki.com.sg/home-appliances/vacuum.html?p=11", "category": "Vacuum"},
{"prod_url": "https://www.bestdenki.com.sg/1104896-karcher-dust-bag-filter-bag-for-wd.html", "site_url": "https://www.bestdenki.com.sg/home-appliances/vacuum.html?p=11", "category": "Vacuum"},
{"prod_url": "https://www.bestdenki.com.sg/1105357-tefal-rechargeable-vac-ty1129.html", "site_url": "https://www.bestdenki.com.sg/home-appliances/vacuum.html?p=11", "category": "Vacuum"}
][
{"prod_url": "https://www.bestdenki.com.sg/1105362-shark-steam-and-scrub-mop-s7001.html", "site_url": "https://www.bestdenki.com.sg/home-appliances/vacuum.html", "category": "vacuum"},
{"prod_url": "https://www.bestdenki.com.sg/1105364-tp-link-robotic-vacuum-tapo-rv10.html", "site_url": "https://www.bestdenki.com.sg/home-appliances/vacuum.html", "category": "vacuum"},
{"prod_url": "https://www.bestdenki.com.sg/1105365-tp-link-robotic-vacuum-tapo-rv10-plus.html", "site_url": "https://www.bestdenki.com.sg/home-appliances/vacuum.html", "category": "vacuum"},
{"prod_url": "https://www.bestdenki.com.sg/1105366-tp-link-robotic-vacuum-tapo-rv30-plus.html", "site_url": "https://www.bestdenki.com.sg/home-appliances/vacuum.html", "category": "vacuum"},
{"prod_url": "https://www.bestdenki.com.sg/1105389-electrolux-rechargeable-vac-efp71512.html", "site_url": "https://www.bestdenki.com.sg/home-appliances/vacuum.html", "category": "vacuum"},
{"prod_url": "https://www.bestdenki.com.sg/1105390-electrolux-rechargeable-vac-efp71525.html", "site_url": "https://www.bestdenki.com.sg/home-appliances/vacuum.html", "category": "vacuum"},
{"prod_url": "https://www.bestdenki.com.sg/1105286-tefal-rechargeable-vac-ty6837.html", "site_url": "https://www.bestdenki.com.sg/home-appliances/vacuum.html", "category": "vacuum"},
{"prod_url": "https://www.bestdenki.com.sg/1105222-shark-steam-mop-s1000.html", "site_url": "https://www.bestdenki.com.sg/home-appliances/vacuum.html", "category": "vacuum"},
{"prod_url": "https://www.bestdenki.com.sg/1105295-dyson-rechargeable-vac-sv10kv8-slim-fluffy-red.html", "site_url": "https://www.bestdenki.com.sg/home-appliances/vacuum.html", "category": "vacuum"},
{"prod_url": "https://www.bestdenki.com.sg/1105394-tefal-rechargeable-vac-gf3039.html", "site_url": "https://www.bestdenki.com.sg/home-appliances/vacuum.html", "category": "vacuum"},
{"prod_url": "https://www.bestdenki.com.sg/1105398-europace-rechargeable-vac-ehva5320.html", "site_url": "https://www.bestdenki.com.sg/home-appliances/vacuum.html", "category": "vacuum"},
{"prod_url": "https://www.bestdenki.com.sg/1105417-philips-rechargeable-vac-xw9383-02.html", "site_url": "https://www.bestdenki.com.sg/home-appliances/vacuum.html", "category": "vacuum"},
{"prod_url": "https://www.bestdenki.com.sg/1105156-shark-cordfree-handheld-vacuum-wv206-pink.html", "site_url": "https://www.bestdenki.com.sg/home-appliances/vacuum.html?p=2", "category": "vacuum"},
{"prod_url": "https://www.bestdenki.com.sg/1105062-philips-bagless-vacuum-xb2023-61.html", "site_url": "https://www.bestdenki.com.sg/home-appliances/vacuum.html?p=2", "category": "vacuum"},
{"prod_url": "https://www.bestdenki.com.sg/1103275-miele-normal-vacuum-complete-c3-marine-blue.html", "site_url": "https://www.bestdenki.com.sg/home-appliances/vacuum.html?p=2", "category": "vacuum"},
{"prod_url": "https://www.bestdenki.com.sg/1103284-karcher-high-pressure-cleaner-k2-compact.html", "site_url": "https://www.bestdenki.com.sg/home-appliances/vacuum.html?p=2", "category": "vacuum"},
{"prod_url": "https://www.bestdenki.com.sg/1103484-karcher-bagless-vacuum-vc3-premium-plus-white.html", "site_url": "https://www.bestdenki.com.sg/home-appliances/vacuum.html?p=2", "category": "vacuum"},
{"prod_url": "https://www.bestdenki.com.sg/1103838-philips-bagless-vacuum-fc9352-61.html", "site_url": "https://www.bestdenki.com.sg/home-appliances/vacuum.html?p=2", "category": "vacuum"},
{"prod_url": "https://www.bestdenki.com.sg/1104024-miele-bagless-vacuum-skcr3-white.html", "site_url": "https://www.bestdenki.com.sg/home-appliances/vacuum.html?p=2", "category": "vacuum"},
{"prod_url": "https://www.bestdenki.com.sg/1104025-miele-bagless-vacuum-skrr3-red.html", "site_url": "https://www.bestdenki.com.sg/home-appliances/vacuum.html?p=2", "category": "vacuum"},
{"prod_url": "https://www.bestdenki.com.sg/1105115-electrolux-rechargeable-vac-pq92-3sbwf.html", "site_url": "https://www.bestdenki.com.sg/home-appliances/vacuum.html?p=2", "category": "vacuum"},
{"prod_url": "https://www.bestdenki.com.sg/1102190-rowenta-dust-bag-zr0039.html", "site_url": "https://www.bestdenki.com.sg/home-appliances/vacuum.html?p=2", "category": "vacuum"},
{"prod_url": "https://www.bestdenki.com.sg/1102228-rowenta-dust-bag-wb4847-endura-wonderbag.html", "site_url": "https://www.bestdenki.com.sg/home-appliances/vacuum.html?p=2", "category": "vacuum"},
{"prod_url": "https://www.bestdenki.com.sg/1102591-karcher-normal-vacuum-se6100.html", "site_url": "https://www.bestdenki.com.sg/home-appliances/vacuum.html?p=2", "category": "vacuum"},
{"prod_url": "https://www.bestdenki.com.sg/1103008-karcher-normal-vacuum-ds6000.html", "site_url": "https://www.bestdenki.com.sg/home-appliances/vacuum.html?p=3", "category": "vacuum"},
{"prod_url": "https://www.bestdenki.com.sg/1103270-miele-normal-vacuum-classic-c1-mango-red.html", "site_url": "https://www.bestdenki.com.sg/home-appliances/vacuum.html?p=3", "category": "vacuum"},
{"prod_url": "https://www.bestdenki.com.sg/1103271-miele-normal-vacuum-compact-c2-marine-blue.html", "site_url": "https://www.bestdenki.com.sg/home-appliances/vacuum.html?p=3", "category": "vacuum"},
{"prod_url": "https://www.bestdenki.com.sg/1103281-karcher-steam-sanitiser-sv7.html", "site_url": "https://www.bestdenki.com.sg/home-appliances/vacuum.html?p=3", "category": "vacuum"},
{"prod_url": "https://www.bestdenki.com.sg/1103470-karcher-canister-type-vac-wd3.html", "site_url": "https://www.bestdenki.com.sg/home-appliances/vacuum.html?p=3", "category": "vacuum"},
{"prod_url": "https://www.bestdenki.com.sg/1103576-tefal-hepa-filter-zr0057.html", "site_url": "https://www.bestdenki.com.sg/home-appliances/vacuum.html?p=3", "category": "vacuum"},
{"prod_url": "https://www.bestdenki.com.sg/1103579-tefal-washable-bag-zr9028.html", "site_url": "https://www.bestdenki.com.sg/home-appliances/vacuum.html?p=3", "category": "vacuum"},
{"prod_url": "https://www.bestdenki.com.sg/1103716-tefal-hygiene-plus-bag-zr2005.html", "site_url": "https://www.bestdenki.com.sg/home-appliances/vacuum.html?p=3", "category": "vacuum"},
{"prod_url": "https://www.bestdenki.com.sg/1103717-tefal-anti-odour-bag-zr2007.html", "site_url": "https://www.bestdenki.com.sg/home-appliances/vacuum.html?p=3", "category": "vacuum"},
{"prod_url": "https://www.bestdenki.com.sg/1103820-tefal-bagless-vacuum-tw3233.html", "site_url": "https://www.bestdenki.com.sg/home-appliances/vacuum.html?p=3", "category": "vacuum"},
{"prod_url": "https://www.bestdenki.com.sg/1103839-philips-bagless-vacuum-fc9350-61.html", "site_url": "https://www.bestdenki.com.sg/home-appliances/vacuum.html?p=3", "category": "vacuum"},
{"prod_url": "https://www.bestdenki.com.sg/1103856-electrolux-normal-vacuum-z1220.html", "site_url": "https://www.bestdenki.com.sg/home-appliances/vacuum.html?p=3", "category": "vacuum"},
{"prod_url": "https://www.bestdenki.com.sg/1104008-electrolux-bagless-vacuum-z1231.html", "site_url": "https://www.bestdenki.com.sg/home-appliances/vacuum.html?p=4", "category": "vacuum"},
{"prod_url": "https://www.bestdenki.com.sg/1104009-karcher-steam-cleaner-sc2-deluxe.html", "site_url": "https://www.bestdenki.com.sg/home-appliances/vacuum.html?p=4", "category": "vacuum"},
{"prod_url": "https://www.bestdenki.com.sg/1104647-miele-normal-vacuum-c3-allergy-powerline-blue.html", "site_url": "https://www.bestdenki.com.sg/home-appliances/vacuum.html?p=4", "category": "vacuum"},
{"prod_url": "https://www.bestdenki.com.sg/1104718-electrolux-bagless-vacuum-ec41-6cr.html", "site_url": "https://www.bestdenki.com.sg/home-appliances/vacuum.html?p=4", "category": "vacuum"},
{"prod_url": "https://www.bestdenki.com.sg/1104886-electrolux-robotic-vacuum-pi92-6sgm.html", "site_url": "https://www.bestdenki.com.sg/home-appliances/vacuum.html?p=4", "category": "vacuum"},
{"prod_url": "https://www.bestdenki.com.sg/1104928-tefal-normal-vacuum-tw2947.html", "site_url": "https://www.bestdenki.com.sg/home-appliances/vacuum.html?p=4", "category": "vacuum"},
{"prod_url": "https://www.bestdenki.com.sg/1104950-karcher-rechargeable-vac-vc4s.html", "site_url": "https://www.bestdenki.com.sg/home-appliances/vacuum.html?p=4", "category": "vacuum"},
{"prod_url": "https://www.bestdenki.com.sg/1105022-tefal-bagless-vacuum-tw4871.html", "site_url": "https://www.bestdenki.com.sg/home-appliances/vacuum.html?p=4", "category": "vacuum"},
{"prod_url": "https://www.bestdenki.com.sg/1105032-miele-normal-vacuum-complete-c3-powerline-grey.html", "site_url": "https://www.bestdenki.com.sg/home-appliances/vacuum.html?p=4", "category": "vacuum"},
{"prod_url": "https://www.bestdenki.com.sg/1105034-tefal-bagless-vacuum-tw7253-exclusive.html", "site_url": "https://www.bestdenki.com.sg/home-appliances/vacuum.html?p=4", "category": "vacuum"},
{"prod_url": "https://www.bestdenki.com.sg/1105051-tefal-bagless-vacuum-tw7260.html", "site_url": "https://www.bestdenki.com.sg/home-appliances/vacuum.html?p=4", "category": "vacuum"},
{"prod_url": "https://www.bestdenki.com.sg/1105052-tefal-bagless-vacuum-tw7689.html", "site_url": "https://www.bestdenki.com.sg/home-appliances/vacuum.html?p=4", "category": "vacuum"},
{"prod_url": "https://www.bestdenki.com.sg/1105053-lg-rechargeable-vac-a9k-ultra.html", "site_url": "https://www.bestdenki.com.sg/home-appliances/vacuum.html?p=5", "category": "vacuum"},
{"prod_url": "https://www.bestdenki.com.sg/1105054-lg-rechargeable-vac-a9k-pro.html", "site_url": "https://www.bestdenki.com.sg/home-appliances/vacuum.html?p=5", "category": "vacuum"},
{"prod_url": "https://www.bestdenki.com.sg/1105055-lg-rechargeable-vac-a9k-core.html", "site_url": "https://www.bestdenki.com.sg/home-appliances/vacuum.html?p=5", "category": "vacuum"},
{"prod_url": "https://www.bestdenki.com.sg/1105058-karcher-handheld-vacuum-vch2.html", "site_url": "https://www.bestdenki.com.sg/home-appliances/vacuum.html?p=5", "category": "vacuum"},
{"prod_url": "https://www.bestdenki.com.sg/1105065-samsung-robotic-vacuum-vr30t85513w-sp.html", "site_url": "https://www.bestdenki.com.sg/home-appliances/vacuum.html?p=5", "category": "vacuum"},
{"prod_url": "https://www.bestdenki.com.sg/1105066-samsung-robotic-vacuum-vr30t80313w-sp.html", "site_url": "https://www.bestdenki.com.sg/home-appliances/vacuum.html?p=5", "category": "vacuum"},
{"prod_url": "https://www.bestdenki.com.sg/1105174-lg-rechargeable-vac-a9t-ultra.html", "site_url": "https://www.bestdenki.com.sg/home-appliances/vacuum.html?p=5", "category": "vacuum"},
{"prod_url": "https://www.bestdenki.com.sg/1105175-shark-wandvac-system-ws632gdsm-gold.html", "site_url": "https://www.bestdenki.com.sg/home-appliances/vacuum.html?p=5", "category": "vacuum"},
{"prod_url": "https://www.bestdenki.com.sg/1105177-shark-wandvac-system-ws632gysm-grey.html", "site_url": "https://www.bestdenki.com.sg/home-appliances/vacuum.html?p=5", "category": "vacuum"},
{"prod_url": "https://www.bestdenki.com.sg/1105178-shark-wandvac-system-ws632rgsm-rose-gold.html", "site_url": "https://www.bestdenki.com.sg/home-appliances/vacuum.html?p=5", "category": "vacuum"},
{"prod_url": "https://www.bestdenki.com.sg/1105424-dyson-rechargeable-vac-v12s-submarine-620h.html", "site_url": "https://www.bestdenki.com.sg/home-appliances/vacuum.html?p=5", "category": "vacuum"},
{"prod_url": "https://www.bestdenki.com.sg/1105435-dyson-rechargeable-vac-sv23-gen5-detect.html", "site_url": "https://www.bestdenki.com.sg/home-appliances/vacuum.html?p=5", "category": "vacuum"},
{"prod_url": "https://www.bestdenki.com.sg/1105436-lg-rechargeable-vac-a9t-steam.html", "site_url": "https://www.bestdenki.com.sg/home-appliances/vacuum.html?p=6", "category": "vacuum"},
{"prod_url": "https://www.bestdenki.com.sg/1105437-lg-rechargeable-vac-a9t-auto.html", "site_url": "https://www.bestdenki.com.sg/home-appliances/vacuum.html?p=6", "category": "vacuum"},
{"prod_url": "https://www.bestdenki.com.sg/1105471-electrolux-rechargeable-vac-efw71711.html", "site_url": "https://www.bestdenki.com.sg/home-appliances/vacuum.html?p=6", "category": "vacuum"},
{"prod_url": "https://www.bestdenki.com.sg/1105473-samsung-rechargeable-vac-vs28c976fqg-sp.html", "site_url": "https://www.bestdenki.com.sg/home-appliances/vacuum.html?p=6", "category": "vacuum"},
{"prod_url": "https://www.bestdenki.com.sg/1105474-samsung-rechargeable-vac-vs28c979fqk-sp.html", "site_url": "https://www.bestdenki.com.sg/home-appliances/vacuum.html?p=6", "category": "vacuum"},
{"prod_url": "https://www.bestdenki.com.sg/1105475-ecovacs-robotic-vacuum-deebot-n10.html", "site_url": "https://www.bestdenki.com.sg/home-appliances/vacuum.html?p=6", "category": "vacuum"},
{"prod_url": "https://www.bestdenki.com.sg/1105476-ecovacs-robotic-vacuum-deebot-t10.html", "site_url": "https://www.bestdenki.com.sg/home-appliances/vacuum.html?p=6", "category": "vacuum"},
{"prod_url": "https://www.bestdenki.com.sg/1105477-ecovacs-robotic-vacuum-deebot-t10-omni.html", "site_url": "https://www.bestdenki.com.sg/home-appliances/vacuum.html?p=6", "category": "vacuum"},
{"prod_url": "https://www.bestdenki.com.sg/1105478-ecovacs-robotic-vacuum-deebot-t20-omni.html", "site_url": "https://www.bestdenki.com.sg/home-appliances/vacuum.html?p=6", "category": "vacuum"},
{"prod_url": "https://www.bestdenki.com.sg/1105481-ecovacs-robotic-vacuum-deebot-x2-omni-black.html", "site_url": "https://www.bestdenki.com.sg/home-appliances/vacuum.html?p=6", "category": "vacuum"},
{"prod_url": "https://www.bestdenki.com.sg/1105443-karcher-rechargeable-vac-vcs3.html", "site_url": "https://www.bestdenki.com.sg/home-appliances/vacuum.html?p=6", "category": "vacuum"},
{"prod_url": "https://www.bestdenki.com.sg/1105447-dyson-rechargeable-vac-sv46v12-fluffy.html", "site_url": "https://www.bestdenki.com.sg/home-appliances/vacuum.html?p=6", "category": "vacuum"},
{"prod_url": "https://www.bestdenki.com.sg/1105448-dyson-rechargeable-vac-sv46v12-absolute.html", "site_url": "https://www.bestdenki.com.sg/home-appliances/vacuum.html?p=7", "category": "vacuum"},
{"prod_url": "https://www.bestdenki.com.sg/1105451-karcher-steam-sanitiser-sc4-deluxe-premium.html", "site_url": "https://www.bestdenki.com.sg/home-appliances/vacuum.html?p=7", "category": "vacuum"},
{"prod_url": "https://www.bestdenki.com.sg/1105462-dyson-rechargeable-vac-sv18-dslim-fluffy-origin.html", "site_url": "https://www.bestdenki.com.sg/home-appliances/vacuum.html?p=7", "category": "vacuum"},
{"prod_url": "https://www.bestdenki.com.sg/1105463-philips-rechargeable-vac-xc7055-01.html", "site_url": "https://www.bestdenki.com.sg/home-appliances/vacuum.html?p=7", "category": "vacuum"},
{"prod_url": "https://www.bestdenki.com.sg/1105464-philips-rechargeable-vac-xw7110-02.html", "site_url": "https://www.bestdenki.com.sg/home-appliances/vacuum.html?p=7", "category": "vacuum"},
{"prod_url": "https://www.bestdenki.com.sg/1105487-tefal-handheld-vacuum-ty20c7.html", "site_url": "https://www.bestdenki.com.sg/home-appliances/vacuum.html?p=7", "category": "vacuum"},
{"prod_url": "https://www.bestdenki.com.sg/1105495-dreame-robotic-vacuum-l10-prime.html", "site_url": "https://www.bestdenki.com.sg/home-appliances/vacuum.html?p=7", "category": "vacuum"},
{"prod_url": "https://www.bestdenki.com.sg/1105497-dreame-rechargeable-vac-h12-pro.html", "site_url": "https://www.bestdenki.com.sg/home-appliances/vacuum.html?p=7", "category": "vacuum"},
{"prod_url": "https://www.bestdenki.com.sg/1105498-dreame-robotic-vacuum-l10s-ultra-se.html", "site_url": "https://www.bestdenki.com.sg/home-appliances/vacuum.html?p=7", "category": "vacuum"},
{"prod_url": "https://www.bestdenki.com.sg/1105499-dreame-robotic-vacuum-l20-ultra.html", "site_url": "https://www.bestdenki.com.sg/home-appliances/vacuum.html?p=7", "category": "vacuum"},
{"prod_url": "https://www.bestdenki.com.sg/1105500-dreame-rechargeable-vac-r10.html", "site_url": "https://www.bestdenki.com.sg/home-appliances/vacuum.html?p=7", "category": "vacuum"},
{"prod_url": "https://www.bestdenki.com.sg/1105501-dreame-rechargeable-vac-r20.html", "site_url": "https://www.bestdenki.com.sg/home-appliances/vacuum.html?p=7", "category": "vacuum"},
{"prod_url": "https://www.bestdenki.com.sg/1105506-samsung-rechargeable-vac-jet-75e-multi-vs20b75aer1-sp.html", "site_url": "https://www.bestdenki.com.sg/home-appliances/vacuum.html?p=8", "category": "vacuum"},
{"prod_url": "https://www.bestdenki.com.sg/1105507-samsung-rechargeable-vac-jet-85-premium-vs20c852ftb-sp.html", "site_url": "https://www.bestdenki.com.sg/home-appliances/vacuum.html?p=8", "category": "vacuum"},
{"prod_url": "https://www.bestdenki.com.sg/1105508-dyson-rechargeable-vac-sv49v12-origin.html", "site_url": "https://www.bestdenki.com.sg/home-appliances/vacuum.html?p=8", "category": "vacuum"},
{"prod_url": "https://www.bestdenki.com.sg/1105522-philips-robotic-vacuum-xu6500-82.html", "site_url": "https://www.bestdenki.com.sg/home-appliances/vacuum.html?p=8", "category": "vacuum"},
{"prod_url": "https://www.bestdenki.com.sg/1105526-sharp-rechargeable-vac-ecsa95s-r.html", "site_url": "https://www.bestdenki.com.sg/home-appliances/vacuum.html?p=8", "category": "vacuum"},
{"prod_url": "https://www.bestdenki.com.sg/1105527-tp-link-robotic-vacuum-tapo-rv30.html", "site_url": "https://www.bestdenki.com.sg/home-appliances/vacuum.html?p=8", "category": "vacuum"},
{"prod_url": "https://www.bestdenki.com.sg/1105530-ecovacs-robotic-vacuum-deebot-x2-omni-white.html", "site_url": "https://www.bestdenki.com.sg/home-appliances/vacuum.html?p=8", "category": "vacuum"},
{"prod_url": "https://www.bestdenki.com.sg/1105532-dreame-rechargeable-vac-h13-pro.html", "site_url": "https://www.bestdenki.com.sg/home-appliances/vacuum.html?p=8", "category": "vacuum"},
{"prod_url": "https://www.bestdenki.com.sg/1105533-dreame-rechargeable-vac-h12s-ae.html", "site_url": "https://www.bestdenki.com.sg/home-appliances/vacuum.html?p=8", "category": "vacuum"},
{"prod_url": "https://www.bestdenki.com.sg/1105537-shark-rechargeable-vac-iw3241sm.html", "site_url": "https://www.bestdenki.com.sg/home-appliances/vacuum.html?p=8", "category": "vacuum"},
{"prod_url": "https://www.bestdenki.com.sg/1105538-shark-rechargeable-vac-iw2241sm.html", "site_url": "https://www.bestdenki.com.sg/home-appliances/vacuum.html?p=8", "category": "vacuum"},
{"prod_url": "https://www.bestdenki.com.sg/1105539-shark-rechargeable-vac-cs851smmvae.html", "site_url": "https://www.bestdenki.com.sg/home-appliances/vacuum.html?p=8", "category": "vacuum"},
{"prod_url": "https://www.bestdenki.com.sg/1105540-shark-rechargeable-vac-cs851smbr.html", "site_url": "https://www.bestdenki.com.sg/home-appliances/vacuum.html?p=9", "category": "vacuum"},
{"prod_url": "https://www.bestdenki.com.sg/0403653-vago-portable-vacuum-tvd2-white.html", "site_url": "https://www.bestdenki.com.sg/home-appliances/vacuum.html?p=9", "category": "vacuum"},
{"prod_url": "https://www.bestdenki.com.sg/0403654-vago-portable-vacuum-tvd2-black.html", "site_url": "https://www.bestdenki.com.sg/home-appliances/vacuum.html?p=9", "category": "vacuum"},
{"prod_url": "https://www.bestdenki.com.sg/0403655-vago-portable-vacuum-tvd2-pink.html", "site_url": "https://www.bestdenki.com.sg/home-appliances/vacuum.html?p=9", "category": "vacuum"},
{"prod_url": "https://www.bestdenki.com.sg/0403656-vago-portable-vacuum-tvd2-purple.html", "site_url": "https://www.bestdenki.com.sg/home-appliances/vacuum.html?p=9", "category": "vacuum"},
{"prod_url": "https://www.bestdenki.com.sg/1105362-shark-steam-and-scrub-mop-s7001.html", "site_url": "https://www.bestdenki.com.sg/home-appliances/vacuum.html?p=9", "category": "vacuum"},
{"prod_url": "https://www.bestdenki.com.sg/1105364-tp-link-robotic-vacuum-tapo-rv10.html", "site_url": "https://www.bestdenki.com.sg/home-appliances/vacuum.html?p=9", "category": "vacuum"},
{"prod_url": "https://www.bestdenki.com.sg/1105365-tp-link-robotic-vacuum-tapo-rv10-plus.html", "site_url": "https://www.bestdenki.com.sg/home-appliances/vacuum.html?p=9", "category": "vacuum"},
{"prod_url": "https://www.bestdenki.com.sg/1105366-tp-link-robotic-vacuum-tapo-rv30-plus.html", "site_url": "https://www.bestdenki.com.sg/home-appliances/vacuum.html?p=9", "category": "vacuum"},
{"prod_url": "https://www.bestdenki.com.sg/1105389-electrolux-rechargeable-vac-efp71512.html", "site_url": "https://www.bestdenki.com.sg/home-appliances/vacuum.html?p=9", "category": "vacuum"},
{"prod_url": "https://www.bestdenki.com.sg/1105390-electrolux-rechargeable-vac-efp71525.html", "site_url": "https://www.bestdenki.com.sg/home-appliances/vacuum.html?p=9", "category": "vacuum"},
{"prod_url": "https://www.bestdenki.com.sg/1105286-tefal-rechargeable-vac-ty6837.html", "site_url": "https://www.bestdenki.com.sg/home-appliances/vacuum.html?p=9", "category": "vacuum"},
{"prod_url": "https://www.bestdenki.com.sg/1105222-shark-steam-mop-s1000.html", "site_url": "https://www.bestdenki.com.sg/home-appliances/vacuum.html?p=10", "category": "vacuum"},
{"prod_url": "https://www.bestdenki.com.sg/1105295-dyson-rechargeable-vac-sv10kv8-slim-fluffy-red.html", "site_url": "https://www.bestdenki.com.sg/home-appliances/vacuum.html?p=10", "category": "vacuum"},
{"prod_url": "https://www.bestdenki.com.sg/1105394-tefal-rechargeable-vac-gf3039.html", "site_url": "https://www.bestdenki.com.sg/home-appliances/vacuum.html?p=10", "category": "vacuum"},
{"prod_url": "https://www.bestdenki.com.sg/1105398-europace-rechargeable-vac-ehva5320.html", "site_url": "https://www.bestdenki.com.sg/home-appliances/vacuum.html?p=10", "category": "vacuum"},
{"prod_url": "https://www.bestdenki.com.sg/1105417-philips-rechargeable-vac-xw9383-02.html", "site_url": "https://www.bestdenki.com.sg/home-appliances/vacuum.html?p=10", "category": "vacuum"},
{"prod_url": "https://www.bestdenki.com.sg/1105419-tefal-rechargeable-vac-ty1238.html", "site_url": "https://www.bestdenki.com.sg/home-appliances/vacuum.html?p=10", "category": "vacuum"},
{"prod_url": "https://www.bestdenki.com.sg/1105316-electrolux-rechargeable-vac-efp31315.html", "site_url": "https://www.bestdenki.com.sg/home-appliances/vacuum.html?p=10", "category": "vacuum"},
{"prod_url": "https://www.bestdenki.com.sg/1105317-electrolux-rechargeable-vac-efp31212.html", "site_url": "https://www.bestdenki.com.sg/home-appliances/vacuum.html?p=10", "category": "vacuum"},
{"prod_url": "https://www.bestdenki.com.sg/1105327-karcher-handheld-vacuum-vcs5.html", "site_url": "https://www.bestdenki.com.sg/home-appliances/vacuum.html?p=10", "category": "vacuum"},
{"prod_url": "https://www.bestdenki.com.sg/1105330-electrolux-dust-bag-e200b-bag.html", "site_url": "https://www.bestdenki.com.sg/home-appliances/vacuum.html?p=10", "category": "vacuum"},
{"prod_url": "https://www.bestdenki.com.sg/1105246-electrolux-bagless-vacuum-efc71622sw.html", "site_url": "https://www.bestdenki.com.sg/home-appliances/vacuum.html?p=10", "category": "vacuum"},
{"prod_url": "https://www.bestdenki.com.sg/1103269-miele-normal-vacuum-classic-c1-lotus-white.html", "site_url": "https://www.bestdenki.com.sg/home-appliances/vacuum.html?p=10", "category": "vacuum"},
{"prod_url": "https://www.bestdenki.com.sg/1101771-rowenta-dust-bag-wb4061-wonderbag.html", "site_url": "https://www.bestdenki.com.sg/home-appliances/vacuum.html?p=11", "category": "vacuum"},
{"prod_url": "https://www.bestdenki.com.sg/1104626-tefal-dust-bag-zr0060.html", "site_url": "https://www.bestdenki.com.sg/home-appliances/vacuum.html?p=11", "category": "vacuum"},
{"prod_url": "https://www.bestdenki.com.sg/1104627-tefal-dust-bag-zr0059.html", "site_url": "https://www.bestdenki.com.sg/home-appliances/vacuum.html?p=11", "category": "vacuum"},
{"prod_url": "https://www.bestdenki.com.sg/1104896-karcher-dust-bag-filter-bag-for-wd.html", "site_url": "https://www.bestdenki.com.sg/home-appliances/vacuum.html?p=11", "category": "vacuum"},
{"prod_url": "https://www.bestdenki.com.sg/1105357-tefal-rechargeable-vac-ty1129.html", "site_url": "https://www.bestdenki.com.sg/home-appliances/vacuum.html?p=11", "category": "vacuum"},
{"prod_url": "https://www.bestdenki.com.sg/1105260-miele-robotic-vacuum-scout-rx3.html", "site_url": "https://www.bestdenki.com.sg/home-appliances/vacuum.html?p=11", "category": "vacuum"},
{"prod_url": "https://www.bestdenki.com.sg/1100322-philips-dust-bag-fc8021.html", "site_url": "https://www.bestdenki.com.sg/home-appliances/vacuum.html?p=11", "category": "vacuum"},
{"prod_url": "https://www.bestdenki.com.sg/1101118-karcher-dust-bag-filter-bag-a2204.html", "site_url": "https://www.bestdenki.com.sg/home-appliances/vacuum.html?p=11", "category": "vacuum"},
{"prod_url": "https://www.bestdenki.com.sg/1101500-hitachi-dust-bag-dustbag-cvsh20v.html", "site_url": "https://www.bestdenki.com.sg/home-appliances/vacuum.html?p=11", "category": "vacuum"},
{"prod_url": "https://www.bestdenki.com.sg/1102998-rowenta-dust-bag-wb305120-compacteo-ergo.html", "site_url": "https://www.bestdenki.com.sg/home-appliances/vacuum.html?p=11", "category": "vacuum"},
{"prod_url": "https://www.bestdenki.com.sg/1103587-karcher-dust-bag-filter-bag-vc2.html", "site_url": "https://www.bestdenki.com.sg/home-appliances/vacuum.html?p=11", "category": "vacuum"},
{"prod_url": "https://www.bestdenki.com.sg/1105271-tefal-rechargeable-vac-ty9670.html", "site_url": "https://www.bestdenki.com.sg/home-appliances/vacuum.html?p=11", "category": "vacuum"},
{"prod_url": "https://www.bestdenki.com.sg/1105273-miele-bagless-vacuum-boost-cx1-parquet.html", "site_url": "https://www.bestdenki.com.sg/home-appliances/vacuum.html?p=12", "category": "vacuum"},
{"prod_url": "https://www.bestdenki.com.sg/1105274-miele-bagless-vacuum-boost-cx1.html", "site_url": "https://www.bestdenki.com.sg/home-appliances/vacuum.html?p=12", "category": "vacuum"},
{"prod_url": "https://www.bestdenki.com.sg/1105275-miele-bagless-vacuum-boost-cx1-cat-dog.html", "site_url": "https://www.bestdenki.com.sg/home-appliances/vacuum.html?p=12", "category": "vacuum"},
{"prod_url": "https://www.bestdenki.com.sg/1105276-yeedi-robotic-vacuum-k650.html", "site_url": "https://www.bestdenki.com.sg/home-appliances/vacuum.html?p=12", "category": "vacuum"},
{"prod_url": "https://www.bestdenki.com.sg/1105277-yeedi-robotic-vacuum-k950.html", "site_url": "https://www.bestdenki.com.sg/home-appliances/vacuum.html?p=12", "category": "vacuum"}
]