[
{"Platform": "COURTS", "Category": "WASHING MACHINES", "Brand": "MIDEA", "Model": "7.5KG TOP LOAD WASHING MACHINE LUNAR DIAL SERIES MA200W75", "Discounted Price": 279.0, "Listed Price": 329.0, "Discount Percentage": 15.2, "Date Collected": "29/02/2024"},
{"Platform": "COURTS", "Category": "WASHING MACHINES", "Brand": "TOSHIBA", "Model": "7KG TOP LOAD WASHING MACHINE AWJ800AS", "Discounted Price": 289.0, "Listed Price": 359.0, "Discount Percentage": 19.5, "Date Collected": "29/02/2024"},
{"Platform": "COURTS", "Category": "WASHING MACHINES", "Brand": "MIDEA", "Model": "8.5KG TOP LOAD WASHING MACHINE LUNAR DIAL SERIES MA200W85", "Discounted Price": 325.0, "Listed Price": 409.0, "Discount Percentage": 20.54, "Date Collected": "29/02/2024"},
{"Platform": "COURTS", "Category": "WASHING MACHINES", "Brand": "PANASONIC", "Model": "7.5KG TOP LOAD WASHING MACHINE NA-75S7HRQ (LIGHT GREY)", "Discounted Price": 365.0, "Listed Price": 449.0, "Discount Percentage": 18.71, "Date Collected": "29/02/2024"},
{"Platform": "COURTS", "Category": "WASHING MACHINES", "Brand": "TOSHIBA", "Model": "8KG TOP LOAD WASHING MACHINE AWJ900DS", "Discounted Price": 369.0, "Listed Price": 449.0, "Discount Percentage": 17.82, "Date Collected": "29/02/2024"},
{"Platform": "COURTS", "Category": "WASHING MACHINES", "Brand": "MIDEA", "Model": "9.5KG TOP LOAD WASHING MACHINE LUNAR DIAL SERIES MA200W95", "Discounted Price": 375.0, "Listed Price": 489.0, "Discount Percentage": 23.31, "Date Collected": "29/02/2024"},
{"Platform": "COURTS", "Category": "WASHING MACHINES", "Brand": "PANASONIC", "Model": "8KG TOP LOAD WASHING MACHINE NA-F80VB7HRQ (LIGHT GREY)", "Discounted Price": 405.0, "Listed Price": 569.0, "Discount Percentage": 28.82, "Date Collected": "29/02/2024"},
{"Platform": "COURTS", "Category": "WASHING MACHINES", "Brand": "MIDEA", "Model": "7KG FRONT LOAD WASHER MFK768W", "Discounted Price": 435.0, "Listed Price": 539.0, "Discount Percentage": 19.29, "Date Collected": "29/02/2024"},
{"Platform": "COURTS", "Category": "WASHING MACHINES", "Brand": "TOSHIBA", "Model": "9KG TOP LOAD WASHING MACHINE AWJ1000FS", "Discounted Price": 435.0, "Listed Price": 519.0, "Discount Percentage": 16.18, "Date Collected": "29/02/2024"},
{"Platform": "COURTS", "Category": "WASHING MACHINES", "Brand": "PANASONIC", "Model": "8KG FRONT LOAD WASHING MACHINE NA-128XB1WSG", "Discounted Price": 509.0, "Listed Price": 659.0, "Discount Percentage": 22.76, "Date Collected": "29/02/2024"},
{"Platform": "COURTS", "Category": "WASHING MACHINES", "Brand": "MIDEA", "Model": "10.5KG TOP LOAD WASHING MACHINE HEALTH GUARD PLUS  MA200W105D", "Discounted Price": 529.0, "Listed Price": 639.0, "Discount Percentage": 17.21, "Date Collected": "29/02/2024"},
{"Platform": "COURTS", "Category": "WASHING MACHINES", "Brand": "MIDEA", "Model": "8KG FRONT LOAD WASHING MACHINE MFK868W", "Discounted Price": 539.0, "Listed Price": 649.0, "Discount Percentage": 16.95, "Date Collected": "29/02/2024"},
{"Platform": "COURTS", "Category": "WASHING MACHINES", "Brand": "TOSHIBA", "Model": "9KG TOP LOAD WASHING MACHINE AWDJ1000FS", "Discounted Price": 545.0, "Listed Price": 659.0, "Discount Percentage": 17.3, "Date Collected": "29/02/2024"},
{"Platform": "COURTS", "Category": "WASHING MACHINES", "Brand": "TOSHIBA", "Model": "8.5KG FRONT LOAD WASHING MACHINE TWBH95S2S", "Discounted Price": 559.0, "Listed Price": 679.0, "Discount Percentage": 17.67, "Date Collected": "29/02/2024"},
{"Platform": "COURTS", "Category": "WASHING MACHINES", "Brand": "MIDEA", "Model": "9KG FRONT LOAD WASHING MACHINE MFK968W", "Discounted Price": 599.0, "Listed Price": 749.0, "Discount Percentage": 20.03, "Date Collected": "29/02/2024"},
{"Platform": "COURTS", "Category": "WASHING MACHINES", "Brand": "MIDEA", "Model": "13KG TOP LOAD WASHING MACHINE HEALTH GUARD PLUS MA200W130D", "Discounted Price": 599.0, "Listed Price": 739.0, "Discount Percentage": 18.94, "Date Collected": "29/02/2024"},
{"Platform": "COURTS", "Category": "WASHING MACHINES", "Brand": "MIDEA", "Model": "8.5KG FRONT LOAD WASHING MACHINE HEALTH GUARD PLUS MF200W85B", "Discounted Price": 599.0, "Listed Price": 699.0, "Discount Percentage": 14.31, "Date Collected": "29/02/2024"},
{"Platform": "COURTS", "Category": "WASHING MACHINES", "Brand": "PANASONIC", "Model": "9.5KG TOP LOAD WASHING MACHINE STAIN CARE NA-FD95X1HRQ (LIGHT GREY)", "Discounted Price": 609.0, "Listed Price": 819.0, "Discount Percentage": 25.64, "Date Collected": "29/02/2024"},
{"Platform": "COURTS", "Category": "WASHING MACHINES", "Brand": "TOSHIBA", "Model": "10.5KG TOP LOAD WASHING MACHINE AW-DUK1150HS", "Discounted Price": 649.0, "Listed Price": 799.0, "Discount Percentage": 18.77, "Date Collected": "29/02/2024"},
{"Platform": "COURTS", "Category": "WASHING MACHINES", "Brand": "TOSHIBA", "Model": "10KG TOP LOAD WASHING MACHINE AW-DUM1100JS", "Discounted Price": 679.0, "Listed Price": 819.0, "Discount Percentage": 17.09, "Date Collected": "29/02/2024"},
{"Platform": "COURTS", "Category": "WASHING MACHINES", "Brand": "TOSHIBA", "Model": "9.5KG FRONT LOAD WASHING MACHINE TW-BL105A4S", "Discounted Price": 699.0, "Listed Price": 849.0, "Discount Percentage": 17.67, "Date Collected": "29/02/2024"},
{"Platform": "COURTS", "Category": "WASHING MACHINES", "Brand": "TOSHIBA", "Model": "12KG TOP LOAD WASHING MACHINE AW-DUK1300KS", "Discounted Price": 719.0, "Listed Price": 879.0, "Discount Percentage": 18.2, "Date Collected": "29/02/2024"},
{"Platform": "COURTS", "Category": "WASHING MACHINES", "Brand": "MIDEA", "Model": "9.5KG FRONT LOAD WASHING MACHINE HEALTH GUARD PLUS MF200W95B", "Discounted Price": 719.0, "Listed Price": 879.0, "Discount Percentage": 18.2, "Date Collected": "29/02/2024"},
{"Platform": "COURTS", "Category": "WASHING MACHINES", "Brand": "PANASONIC", "Model": "10KG TOP LOAD WASHING MACHINE STAIN CARE NA-FD10V1BRQ (BLACK SLIVER)", "Discounted Price": 725.0, "Listed Price": 999.0, "Discount Percentage": 27.43, "Date Collected": "29/02/2024"},
{"Platform": "COURTS", "Category": "WASHING MACHINES", "Brand": "PANASONIC", "Model": "11.5KG TOP LOAD WASHER NA-FD115X3BQ", "Discounted Price": 739.0, "Listed Price": 999.0, "Discount Percentage": 26.03, "Date Collected": "29/02/2024"},
{"Platform": "COURTS", "Category": "WASHING MACHINES", "Brand": "TOSHIBA", "Model": "8.5KG FRONT LOAD WASHING MACHINE TW-BK95G4S", "Discounted Price": 765.0, "Listed Price": 959.0, "Discount Percentage": 20.23, "Date Collected": "29/02/2024"},
{"Platform": "COURTS", "Category": "WASHING MACHINES", "Brand": "TOSHIBA", "Model": "10.5KG FRONT LOAD WASHING MACHINE TW-BL115A2S", "Discounted Price": 799.0, "Listed Price": 949.0, "Discount Percentage": 15.81, "Date Collected": "29/02/2024"},
{"Platform": "COURTS", "Category": "WASHING MACHINES", "Brand": "PANASONIC", "Model": "12.5KG TOP LOAD WASHER NA-FD125V3BQ", "Discounted Price": 819.0, "Listed Price": 1189.0, "Discount Percentage": 31.12, "Date Collected": "29/02/2024"},
{"Platform": "COURTS", "Category": "WASHING MACHINES", "Brand": "TOSHIBA", "Model": "9.5KG FRONT LOAD WASHING MACHINE TW-BK105G4S", "Discounted Price": 885.0, "Listed Price": 1079.0, "Discount Percentage": 17.98, "Date Collected": "29/02/2024"},
{"Platform": "COURTS", "Category": "WASHING MACHINES", "Brand": "PANASONIC", "Model": "9KG HYGIENE CARE FRONT LOAD WASHING MACHINE WITH DRY ASSIST NA-V90FC1WSG (WHITE)", "Discounted Price": 915.0, "Listed Price": 1299.0, "Discount Percentage": 29.56, "Date Collected": "29/02/2024"},
{"Platform": "COURTS", "Category": "WASHING MACHINES", "Brand": "TOSHIBA", "Model": "9.5KG/7KG WASHER DRYER COMBO WITH SMART WIFI CONTROL TWD-BM105GF4S (MORANDI GRAY)", "Discounted Price": 1019.0, "Listed Price": 1259.0, "Discount Percentage": 19.06, "Date Collected": "29/02/2024"},
{"Platform": "COURTS", "Category": "WASHING MACHINES", "Brand": "PANASONIC", "Model": "13.5KG TOP LOAD WASHER NA-FD135Z3BQ", "Discounted Price": 1089.0, "Listed Price": 1519.0, "Discount Percentage": 28.31, "Date Collected": "29/02/2024"},
{"Platform": "COURTS", "Category": "WASHING MACHINES", "Brand": "PANASONIC", "Model": "11KG FRONT LOAD WASHING MACHINE HYGIENE CARE NA-V11FG2WSG (WHITE)", "Discounted Price": 1099.0, "Listed Price": 1499.0, "Discount Percentage": 26.68, "Date Collected": "29/02/2024"},
{"Platform": "COURTS", "Category": "WASHING MACHINES", "Brand": "PANASONIC", "Model": "13.5KG TOP LOAD WASHER NA-FD135X3BQ", "Discounted Price": 1121.0, "Listed Price": 1409.0, "Discount Percentage": 20.44, "Date Collected": "29/02/2024"},
{"Platform": "COURTS", "Category": "WASHING MACHINES", "Brand": "TOSHIBA", "Model": "10.5KG/7KG FRONT LOAD WASHER DYER COMBO SMART WIFI CONTROL TWD-BM115GF4S (BLACK)", "Discounted Price": 1169.0, "Listed Price": 1419.0, "Discount Percentage": 17.62, "Date Collected": "29/02/2024"},
{"Platform": "COURTS", "Category": "WASHING MACHINES", "Brand": "PANASONIC", "Model": "10KG HYGIENE CARE FRONT LOAD WASHING MACHINE NA-V10FR1BSG (10KG)", "Discounted Price": 1189.0, "Listed Price": 1739.0, "Discount Percentage": 31.63, "Date Collected": "29/02/2024"},
{"Platform": "COURTS", "Category": "WASHING MACHINES", "Brand": "PANASONIC", "Model": "16KG TOP LOAD WASHING MACHINE FOR SPEICAL STAIN CARE NA-FD16V1BRQ (BLACK SLIVER)", "Discounted Price": 1189.0, "Listed Price": 1599.0, "Discount Percentage": 25.64, "Date Collected": "29/02/2024"},
{"Platform": "COURTS", "Category": "WASHING MACHINES", "Brand": "WHIRLPOOL", "Model": "10.5KG SUPREME OXYCARE FRONT LOAD WASHER  FWMD10502GW", "Discounted Price": 1349.0, "Listed Price": 1519.0, "Discount Percentage": 11.19, "Date Collected": "29/02/2024"},
{"Platform": "COURTS", "Category": "WASHING MACHINES", "Brand": "TOSHIBA", "Model": " 12.5KG/8KG WASHER DRYER COMBO WITH SMART WIFI CONTRO TWD-BM135GF4S (BLACK)", "Discounted Price": 1359.0, "Listed Price": 1669.0, "Discount Percentage": 18.57, "Date Collected": "29/02/2024"},
{"Platform": "COURTS", "Category": "WASHING MACHINES", "Brand": "LG", "Model": "T2108NT1G TOP LOAD WASHER (8KG)", "Discounted Price": 419.0, "Listed Price": 549.0, "Discount Percentage": 23.68, "Date Collected": "29/02/2024"},
{"Platform": "COURTS", "Category": "WASHING MACHINES", "Brand": "ELECTROLUX", "Model": "8.5KG ELITE CARE TOP LOAD WASHING MACHINE EWT8588H1WB", "Discounted Price": 439.0, "Listed Price": 749.0, "Discount Percentage": 41.39, "Date Collected": "29/02/2024"},
{"Platform": "COURTS", "Category": "WASHING MACHINES", "Brand": "ELECTROLUX", "Model": "10.5KG TOP LOAD WASHING MACHINE EWT0H88H1WB", "Discounted Price": 559.0, "Listed Price": 959.0, "Discount Percentage": 41.71, "Date Collected": "29/02/2024"},
{"Platform": "COURTS", "Category": "WASHING MACHINES", "Brand": "ELECTROLUX", "Model": "8KG FRONT LOAD WASHING MACHINE EWF8025DGWA", "Discounted Price": 609.0, "Listed Price": 1169.0, "Discount Percentage": 47.9, "Date Collected": "29/02/2024"},
{"Platform": "COURTS", "Category": "WASHING MACHINES", "Brand": "ELECTROLUX", "Model": "8KG FRONT LOAD WASHER EWF8024D3WB (WHITE)", "Discounted Price": 819.0, "Listed Price": 1329.0, "Discount Percentage": 38.37, "Date Collected": "29/02/2024"},
{"Platform": "COURTS", "Category": "WASHING MACHINES", "Brand": "WHIRLPOOL", "Model": "10.5KG FRONT LOAD WASHING MACHINE FWEB10502GW", "Discounted Price": 949.0, "Listed Price": 1059.0, "Discount Percentage": 10.39, "Date Collected": "29/02/2024"},
{"Platform": "COURTS", "Category": "WASHING MACHINES", "Brand": "FISHER & PAYKEL", "Model": "9KG TOP LOAD WASHING MACHINE WA9060G1 (WHITE)", "Discounted Price": 949.0, "Listed Price": 1109.0, "Discount Percentage": 14.43, "Date Collected": "29/02/2024"},
{"Platform": "COURTS", "Category": "WASHING MACHINES", "Brand": "EUROPACE", "Model": "EFW 9101Y FRONT LOAD WASHER (10KG)", "Discounted Price": 969.0, "Listed Price": 1299.0, "Discount Percentage": 25.4, "Date Collected": "29/02/2024"},
{"Platform": "COURTS", "Category": "WASHING MACHINES", "Brand": "WHIRLPOOL", "Model": "9KG FRONT LOAD WASHING MACHINE FWG91284W", "Discounted Price": 998.0, "Listed Price": 1109.0, "Discount Percentage": 10.01, "Date Collected": "29/02/2024"},
{"Platform": "COURTS", "Category": "WASHING MACHINES", "Brand": "ELECTROLUX", "Model": "9KG FRONT LOAD WASHING MACHINE EWF9024D3WB", "Discounted Price": 1019.0, "Listed Price": 1559.0, "Discount Percentage": 34.64, "Date Collected": "29/02/2024"},
{"Platform": "COURTS", "Category": "WASHING MACHINES", "Brand": "PANASONIC", "Model": "10KG HYGIENE CARE FRONT LOAD WASHING MACHINE WITH DRY ASSIST  NA-V10FC1WSG (WHITE)", "Discounted Price": 1189.0, "Listed Price": 1599.0, "Discount Percentage": 25.64, "Date Collected": "29/02/2024"},
{"Platform": "COURTS", "Category": "WASHING MACHINES", "Brand": "PANASONIC", "Model": "9KG HYGIENE CARE FRONT LOAD WASHING MACHINE WITH DRY ASSIST NA-V90FR1BSG (BLACK)", "Discounted Price": 1199.0, "Listed Price": 1439.0, "Discount Percentage": 16.68, "Date Collected": "29/02/2024"},
{"Platform": "COURTS", "Category": "WASHING MACHINES", "Brand": "FISHER & PAYKEL", "Model": "10KG TOP LOAD WASHING MACHINE WA1060G1 (WHITE)", "Discounted Price": 1199.0, "Listed Price": 1210.0, "Discount Percentage": 0.91, "Date Collected": "29/02/2024"},
{"Platform": "COURTS", "Category": "WASHING MACHINES", "Brand": "ELECTROLUX", "Model": "14KG TOP LOAD WASHING MACHINE ULTIMATECARE 700 EWT1474M7SA", "Discounted Price": 1249.0, "Listed Price": 1459.0, "Discount Percentage": 14.39, "Date Collected": "29/02/2024"},
{"Platform": "COURTS", "Category": "WASHING MACHINES", "Brand": "PANASONIC", "Model": "11KG FRONT LOAD WASHING MACHINE SPECIAL HYGIENE CARE NA-V11FX2LSG (SUS SILVER LOOK)", "Discounted Price": 1299.0, "Listed Price": 1599.0, "Discount Percentage": 18.76, "Date Collected": "29/02/2024"},
{"Platform": "COURTS", "Category": "WASHING MACHINES", "Brand": "FISHER & PAYKEL", "Model": "10KG TOP LOAD WASHING MACHINE WA1060E3 (WHITE)", "Discounted Price": 1299.0, "Listed Price": 1311.0, "Discount Percentage": 0.92, "Date Collected": "29/02/2024"},
{"Platform": "COURTS", "Category": "WASHING MACHINES", "Brand": "ELECTROLUX", "Model": "10KG FRONT LOAD WASHING MACHINE EWF1024P5WB", "Discounted Price": 1329.0, "Listed Price": 2169.0, "Discount Percentage": 38.73, "Date Collected": "29/02/2024"},
{"Platform": "COURTS", "Category": "WASHING MACHINES", "Brand": "FISHER & PAYKEL", "Model": "11KG FRONT LOAD WASHING MACHINE STREAM CARE WH1160P3 (WHITE)", "Discounted Price": 1599.0, "Listed Price": 2220.0, "Discount Percentage": 27.97, "Date Collected": "29/02/2024"},
{"Platform": "COURTS", "Category": "WASHING MACHINES", "Brand": "ELECTROLUX", "Model": "11KG FRONT LOAD WASHING MACHINE EWF1142Q7WB", "Discounted Price": 1659.0, "Listed Price": 2989.0, "Discount Percentage": 44.5, "Date Collected": "29/02/2024"},
{"Platform": "COURTS", "Category": "WASHING MACHINES", "Brand": "BOSCH", "Model": "9KG FRONT LOAD WASHING MACHINE WGG244A0SG", "Discounted Price": 1688.0, "Listed Price": 2999.0, "Discount Percentage": 43.71, "Date Collected": "29/02/2024"},
{"Platform": "COURTS", "Category": "WASHING MACHINES", "Brand": "ELECTROLUX", "Model": "11KG FRONT LOAD WASHING MACHINE EWF1141R9WB", "Discounted Price": 1869.0, "Listed Price": 3409.0, "Discount Percentage": 45.17, "Date Collected": "29/02/2024"},
{"Platform": "COURTS", "Category": "WASHING MACHINES", "Brand": "BOSCH", "Model": "10KG FRONT LOAD WASHER WGA25400SG", "Discounted Price": 1999.0, "Listed Price": 3099.0, "Discount Percentage": 35.5, "Date Collected": "29/02/2024"},
{"Platform": "COURTS", "Category": "WASHING MACHINES", "Brand": "BOSCH", "Model": "9KG FRONT LOAD WASHING MACHINE WAW28480SG", "Discounted Price": 2199.0, "Listed Price": 3599.0, "Discount Percentage": 38.9, "Date Collected": "29/02/2024"},
{"Platform": "COURTS", "Category": "WASHING MACHINES", "Brand": "FISHER & PAYKEL", "Model": "12KG FRONT LOAD WASHING MACHINE ACTIVEINTELLIGENCE\u2122 STREAM CARE WH1260F2 (WHITE)", "Discounted Price": 2299.0, "Listed Price": 2623.0, "Discount Percentage": 12.35, "Date Collected": "29/02/2024"},
{"Platform": "COURTS", "Category": "WASHING MACHINES", "Brand": "BOSCH", "Model": "WAU28PH0SG FRONT LOAD WASHER (9KG)", "Discounted Price": 2488.0, "Listed Price": 4899.0, "Discount Percentage": 49.21, "Date Collected": "29/02/2024"},
{"Platform": "COURTS", "Category": "WASHING MACHINES", "Brand": "FISHER & PAYKEL", "Model": "12KG FRONT LOAD WASHING MACHINE ACTIVEINTELLIGENCE\u2122 STREAM CARE WH1260F2 (WHITE)", "Discounted Price": 2299.0, "Listed Price": 2623.0, "Discount Percentage": 12.35, "Date Collected": "29/02/2024"},
{"Platform": "COURTS", "Category": "WASHING MACHINES", "Brand": "BOSCH", "Model": "WAU28PH0SG FRONT LOAD WASHER (9KG)", "Discounted Price": 2488.0, "Listed Price": 4899.0, "Discount Percentage": 49.21, "Date Collected": "29/02/2024"},
{"Platform": "COURTS", "Category": "WASHING MACHINES", "Brand": "SHOWY", "Model": "5154200/5154400 3/4 IN C.P GARDEN TAP NOZZLE", "Discounted Price": 4.1, "Listed Price": 4.1, "Discount Percentage": 0, "Date Collected": "29/02/2024"},
{"Platform": "COURTS", "Category": "WASHING MACHINES", "Brand": "BOSCH", "Model": "WTZ27410 STACKING KIT FOR WTW87561GB / WTR85V00SG / WTW85400SG", "Discounted Price": 35.0, "Listed Price": 35.0, "Discount Percentage": 0, "Date Collected": "29/02/2024"},
{"Platform": "COURTS", "Category": "WASHING MACHINES", "Brand": "ELECTROLUX", "Model": "4500003 UNIVERSAL STACKING KIT", "Discounted Price": 65.0, "Listed Price": 65.0, "Discount Percentage": 0, "Date Collected": "29/02/2024"},
{"Platform": "COURTS", "Category": "WASHING MACHINES", "Brand": "WHIRLPOOL", "Model": "KCL 103 STACKING KIT", "Discounted Price": 110.0, "Listed Price": 110.0, "Discount Percentage": 0, "Date Collected": "29/02/2024"},
{"Platform": "COURTS", "Category": "WASHING MACHINES", "Brand": "WHIRLPOOL", "Model": "SKS101 WHIRLPOOL STACKING KIT WHP DRYER SK PWP", "Discounted Price": 140.0, "Listed Price": 140.0, "Discount Percentage": 0, "Date Collected": "29/02/2024"},
{"Platform": "COURTS", "Category": "WASHING MACHINES", "Brand": "SHARP", "Model": "7KG TOP LOAD WASHING MACHINE ES-G70G (DARK GREY)", "Discounted Price": 302.0, "Listed Price": 321.0, "Discount Percentage": 5.92, "Date Collected": "29/02/2024"},
{"Platform": "COURTS", "Category": "WASHING MACHINES", "Brand": "TECNO", "Model": "9KG TOP LOAD WASHING MACHINE TWS9090", "Discounted Price": 318.0, "Listed Price": 318.0, "Discount Percentage": 0, "Date Collected": "29/02/2024"},
{"Platform": "COURTS", "Category": "WASHING MACHINES", "Brand": "SHARP", "Model": "8KG TOP LOAD WASHING MACHINE ES-G80G", "Discounted Price": 352.0, "Listed Price": 374.0, "Discount Percentage": 5.88, "Date Collected": "29/02/2024"},
{"Platform": "COURTS", "Category": "WASHING MACHINES", "Brand": "TECNO", "Model": "6KG TOP LOAD WASHER TWA6068", "Discounted Price": 358.0, "Listed Price": 358.0, "Discount Percentage": 0, "Date Collected": "29/02/2024"},
{"Platform": "COURTS", "Category": "WASHING MACHINES", "Brand": "EUROPACE", "Model": "8KG TOP LOAD WASHING MACHINE ETW7800T", "Discounted Price": 389.0, "Listed Price": 499.0, "Discount Percentage": 22.04, "Date Collected": "29/02/2024"},
{"Platform": "COURTS", "Category": "WASHING MACHINES", "Brand": "SHARP", "Model": "9KG TOP LOAD WASHING MACHINE ES-G90G", "Discounted Price": 403.0, "Listed Price": 429.0, "Discount Percentage": 6.06, "Date Collected": "29/02/2024"},
{"Platform": "COURTS", "Category": "WASHING MACHINES", "Brand": "SAMSUNG", "Model": "7.5KG TOP LOAD WASHING MACHINE WOBBLE\u2122 TECHNOLOGY WA75H4400SS/SP (SILVER)", "Discounted Price": 403.0, "Listed Price": 403.0, "Discount Percentage": 0, "Date Collected": "29/02/2024"},
{"Platform": "COURTS", "Category": "WASHING MACHINES", "Brand": "WHIRLPOOL", "Model": "9KG TOP LOAD WASHING MACHINE WVFC900AJGR", "Discounted Price": 459.0, "Listed Price": 459.0, "Discount Percentage": 0, "Date Collected": "29/02/2024"},
{"Platform": "COURTS", "Category": "WASHING MACHINES", "Brand": "TECNO", "Model": "8KG TOP LOAD WASHING MACHINE TWA8088", "Discounted Price": 498.0, "Listed Price": 498.0, "Discount Percentage": 0, "Date Collected": "29/02/2024"},
{"Platform": "COURTS", "Category": "WASHING MACHINES", "Brand": "LG", "Model": "8KG SMART INVERTER TOP LOAD WASHING MACHINE  T2108VSAW (BLUE WHITE)", "Discounted Price": 560.0, "Listed Price": 672.0, "Discount Percentage": 16.67, "Date Collected": "29/02/2024"},
{"Platform": "COURTS", "Category": "WASHING MACHINES", "Brand": "BEKO", "Model": "WTLJI10C1SS TOP LOAD WASHER (10KG)", "Discounted Price": 569.0, "Listed Price": 799.0, "Discount Percentage": 28.79, "Date Collected": "29/02/2024"},
{"Platform": "COURTS", "Category": "WASHING MACHINES", "Brand": "HITACHI", "Model": "9KG TOP LOADING WASHER BEAT WAVE WASH SF90XA (WHITE)", "Discounted Price": 569.0, "Listed Price": 649.0, "Discount Percentage": 12.33, "Date Collected": "29/02/2024"},
{"Platform": "COURTS", "Category": "WASHING MACHINES", "Brand": "TECNO", "Model": "10KG TOP LOAD WASHING MACHINE TWA1099", "Discounted Price": 598.0, "Listed Price": 598.0, "Discount Percentage": 0, "Date Collected": "29/02/2024"},
{"Platform": "COURTS", "Category": "WASHING MACHINES", "Brand": "SHARP", "Model": "8.5KG TOP LOAD WASHING MACHINE ES-W85TWXT-SA", "Discounted Price": 605.0, "Listed Price": 644.0, "Discount Percentage": 6.06, "Date Collected": "29/02/2024"},
{"Platform": "COURTS", "Category": "WASHING MACHINES", "Brand": "SAMSUNG", "Model": "8.5KG TOP LOAD WASHER WA85CG4545BDSP (VERSAILLES GRAY)", "Discounted Price": 605.0, "Listed Price": 605.0, "Discount Percentage": 0, "Date Collected": "29/02/2024"},
{"Platform": "COURTS", "Category": "WASHING MACHINES", "Brand": "SHARP", "Model": "9.5KG TOP LOAD WASHING MACHINE ES-W95TWXT-SA", "Discounted Price": 655.0, "Listed Price": 697.0, "Discount Percentage": 6.03, "Date Collected": "29/02/2024"},
{"Platform": "COURTS", "Category": "WASHING MACHINES", "Brand": "SHARP", "Model": "10KG TOP LOAD WASHING MACHINE ES-F100G", "Discounted Price": 655.0, "Listed Price": 697.0, "Discount Percentage": 6.03, "Date Collected": "29/02/2024"},
{"Platform": "COURTS", "Category": "WASHING MACHINES", "Brand": "SAMSUNG", "Model": "9KG TOP LOAD WASHER WA90CG4545BDSP (VERSAILLES GRAY)", "Discounted Price": 656.0, "Listed Price": 656.0, "Discount Percentage": 0, "Date Collected": "29/02/2024"},
{"Platform": "COURTS", "Category": "WASHING MACHINES", "Brand": "SHARP", "Model": "ES-X155 TOP LOAD WASHER (15.5KG)", "Discounted Price": 699.0, "Listed Price": 744.0, "Discount Percentage": 6.05, "Date Collected": "29/02/2024"},
{"Platform": "COURTS", "Category": "WASHING MACHINES", "Brand": "SHARP", "Model": "10.5KG TOP LOAD WASHING MACHINE ES-W105TWXT-SA", "Discounted Price": 705.0, "Listed Price": 750.0, "Discount Percentage": 6.0, "Date Collected": "29/02/2024"},
{"Platform": "COURTS", "Category": "WASHING MACHINES", "Brand": "HITACHI", "Model": "11KG TOP LOADING WASHER DYNAMIC-STREAM WASH SF110XA (COOL GRAY)", "Discounted Price": 709.0, "Listed Price": 899.0, "Discount Percentage": 21.13, "Date Collected": "29/02/2024"},
{"Platform": "COURTS", "Category": "WASHING MACHINES", "Brand": "BEKO", "Model": "8KG/1200 RPM FREESTANDING FRONT LOAD WASHING MACHINE WCV8746X0 (WHITE)", "Discounted Price": 739.0, "Listed Price": 1099.0, "Discount Percentage": 32.76, "Date Collected": "29/02/2024"},
{"Platform": "COURTS", "Category": "WASHING MACHINES", "Brand": "BEKO", "Model": "12KG AUTOMATIC TOP LOAD WASHING MACHINE WTLI120D (DARK GREY)", "Discounted Price": 759.0, "Listed Price": 899.0, "Discount Percentage": 15.57, "Date Collected": "29/02/2024"},
{"Platform": "COURTS", "Category": "WASHING MACHINES", "Brand": "ELECTROLUX", "Model": "10KG TOP LOAD WASHING MACHINE ULTIMATECARE EWT1074M5WA (WHITE)", "Discounted Price": 799.0, "Listed Price": 989.0, "Discount Percentage": 19.21, "Date Collected": "29/02/2024"},
{"Platform": "COURTS", "Category": "WASHING MACHINES", "Brand": "CANDY", "Model": "10KG TOP LOAD WASHING MACHINE CATL6108GVSI", "Discounted Price": 799.0, "Listed Price": 899.0, "Discount Percentage": 11.12, "Date Collected": "29/02/2024"},
{"Platform": "COURTS", "Category": "WASHING MACHINES", "Brand": "SHARP", "Model": "8.5KG FRONT LOAD WASHING MACHINE ES-FW85SG", "Discounted Price": 806.0, "Listed Price": 857.0, "Discount Percentage": 5.95, "Date Collected": "29/02/2024"},
{"Platform": "COURTS", "Category": "WASHING MACHINES", "Brand": "SHARP", "Model": "8KG FRONT LOAD WASHING MACHINE ES-HFH814AW3", "Discounted Price": 806.0, "Listed Price": 857.0, "Discount Percentage": 5.95, "Date Collected": "29/02/2024"},
{"Platform": "COURTS", "Category": "WASHING MACHINES", "Brand": "SAMSUNG", "Model": "10KG TOP LOAD WASHER WA10CG4545BVSP (BLACK CAVIAR)", "Discounted Price": 807.0, "Listed Price": 807.0, "Discount Percentage": 0, "Date Collected": "29/02/2024"},
{"Platform": "COURTS", "Category": "WASHING MACHINES", "Brand": "SAMSUNG", "Model": "7.5KG FRONT LOAD WASHING MACHINE ECOBUBBLE\u2122 WW75TA046TE/SP (WHITE)", "Discounted Price": 807.0, "Listed Price": 807.0, "Discount Percentage": 0, "Date Collected": "29/02/2024"},
{"Platform": "COURTS", "Category": "WASHING MACHINES", "Brand": "LG", "Model": "8KG FRONT LOAD WASHING MACHINE AI DIRECTDRIVE\u2122 FV1208S5W (WHITE)", "Discounted Price": 835.0, "Listed Price": 1252.0, "Discount Percentage": 33.31, "Date Collected": "29/02/2024"},
{"Platform": "COURTS", "Category": "WASHING MACHINES", "Brand": "WHIRLPOOL", "Model": "9KG FRONT LOAD WASHING MACHINE FWEB9002GW", "Discounted Price": 849.0, "Listed Price": 907.0, "Discount Percentage": 6.39, "Date Collected": "29/02/2024"},
{"Platform": "COURTS", "Category": "WASHING MACHINES", "Brand": "LG", "Model": "2.5KG MINI WASHING MACHINE WITH SLIM INVERTER TWINWASH\u2122 TV2425NTWB (BLACK)", "Discounted Price": 849.0, "Listed Price": 1028.0, "Discount Percentage": 17.41, "Date Collected": "29/02/2024"},
{"Platform": "COURTS", "Category": "WASHING MACHINES", "Brand": "BEKO", "Model": "8KG/1200 RPM FREESTANDING FRONT LOAD WASHING MACHINE WCV8736XS0 (WHITE)", "Discounted Price": 869.0, "Listed Price": 999.0, "Discount Percentage": 13.01, "Date Collected": "29/02/2024"},
{"Platform": "COURTS", "Category": "WASHING MACHINES", "Brand": "WHIRLPOOL", "Model": "9KG FWEB9002GG SANICARE BRUSHLESS INVERTER MOTOR", "Discounted Price": 899.0, "Listed Price": 999.0, "Discount Percentage": 10.01, "Date Collected": "29/02/2024"},
{"Platform": "COURTS", "Category": "WASHING MACHINES", "Brand": "BEKO", "Model": "9KG/1400 RPM FREESTANDING FRONT LOAD WASHING MACHINE WCV9746X0 (WHITE)", "Discounted Price": 899.0, "Listed Price": 1199.0, "Discount Percentage": 25.02, "Date Collected": "29/02/2024"},
{"Platform": "COURTS", "Category": "WASHING MACHINES", "Brand": "LG", "Model": "2.5KG MINI WASHER T2525NTWV", "Discounted Price": 916.0, "Listed Price": 1018.0, "Discount Percentage": 10.02, "Date Collected": "29/02/2024"},
{"Platform": "COURTS", "Category": "WASHING MACHINES", "Brand": "LG", "Model": "8.5KG FRONT LOAD WASHING MACHINE SLIM AI DIRECTDRIVE\u2122 FV1285S4W (WHITE)", "Discounted Price": 947.0, "Listed Price": 1609.0, "Discount Percentage": 41.14, "Date Collected": "29/02/2024"},
{"Platform": "COURTS", "Category": "WASHING MACHINES", "Brand": "LG", "Model": "10KG TOP LOAD WASHING MACHINE TURBOWASH3D\u2122 TH2110DSAW (WHITE)", "Discounted Price": 949.0, "Listed Price": 1293.0, "Discount Percentage": 26.6, "Date Collected": "29/02/2024"},
{"Platform": "COURTS", "Category": "WASHING MACHINES", "Brand": "TOSHIBA", "Model": "11KG TOP LOAD WASHING MACHINE AWDUH1200GS", "Discounted Price": 963.0, "Listed Price": 1221.0, "Discount Percentage": 21.13, "Date Collected": "29/02/2024"},
{"Platform": "COURTS", "Category": "WASHING MACHINES", "Brand": "SAMSUNG", "Model": "8KG FRONT LOAD WASHING MACHINE ECOBUBBLE\u2122 WW80T534DTT/SP (WHITE)", "Discounted Price": 968.0, "Listed Price": 968.0, "Discount Percentage": 0, "Date Collected": "29/02/2024"},
{"Platform": "COURTS", "Category": "WASHING MACHINES", "Brand": "HITACHI", "Model": "13KG TOP LOAD WASHING MACHINE SF130TCV", "Discounted Price": 999.0, "Listed Price": 1399.0, "Discount Percentage": 28.59, "Date Collected": "29/02/2024"},
{"Platform": "COURTS", "Category": "WASHING MACHINES", "Brand": "HITACHI", "Model": "14KG TOP LOAD WASHING MACHINE SF140XAV", "Discounted Price": 999.0, "Listed Price": 1399.0, "Discount Percentage": 28.59, "Date Collected": "29/02/2024"},
{"Platform": "COURTS", "Category": "WASHING MACHINES", "Brand": "BEKO", "Model": "9KG/1200 RPM FREESTANDING FRONT LOAD WASHING MACHINE WCV8736XS0 (WHITE)", "Discounted Price": 999.0, "Listed Price": 1149.0, "Discount Percentage": 13.05, "Date Collected": "29/02/2024"},
{"Platform": "COURTS", "Category": "WASHING MACHINES", "Brand": "CANDY", "Model": "9KG FRONT LOAD WASHING MACHINE INVERTER RAPIDO RO1696DWMCE/1-80", "Discounted Price": 1009.0, "Listed Price": 1399.0, "Discount Percentage": 27.88, "Date Collected": "29/02/2024"},
{"Platform": "COURTS", "Category": "WASHING MACHINES", "Brand": "SAMSUNG", "Model": "12KG TOP LOAD WASHER WA12CG5886BVSP (BLACK CAVIAR)", "Discounted Price": 1009.0, "Listed Price": 1009.0, "Discount Percentage": 0, "Date Collected": "29/02/2024"},
{"Platform": "COURTS", "Category": "WASHING MACHINES", "Brand": "WHIRLPOOL", "Model": "10.5KG TOP LOAD WASHING MACHINE WVTD1050AHG", "Discounted Price": 1017.0, "Listed Price": 1017.0, "Discount Percentage": 0, "Date Collected": "29/02/2024"},
{"Platform": "COURTS", "Category": "WASHING MACHINES", "Brand": "LG", "Model": "8KG FRONT LOAD WASHING MACHINE AI DIRECTDRIVE\u2122 FV1408S4W (WHITE)", "Discounted Price": 1049.0, "Listed Price": 1782.0, "Discount Percentage": 41.13, "Date Collected": "29/02/2024"},
{"Platform": "COURTS", "Category": "WASHING MACHINES", "Brand": "SHARP", "Model": "9.5KG FRONT LOAD WASHER ES-FW95SG", "Discounted Price": 1109.0, "Listed Price": 1180.0, "Discount Percentage": 6.02, "Date Collected": "29/02/2024"},
{"Platform": "COURTS", "Category": "WASHING MACHINES", "Brand": "SAMSUNG", "Model": "14KG TOP LOAD WASHER WA14CG5886BVSP (BLACK CAVIA)", "Discounted Price": 1110.0, "Listed Price": 1110.0, "Discount Percentage": 0, "Date Collected": "29/02/2024"},
{"Platform": "COURTS", "Category": "WASHING MACHINES", "Brand": "SAMSUNG", "Model": "8KG FRONT LOAD WASHING MACHINE QUICKDRIVE\u2122 WW80T754DWH/SP (WHITE)", "Discounted Price": 1170.0, "Listed Price": 1170.0, "Discount Percentage": 0, "Date Collected": "29/02/2024"},
{"Platform": "COURTS", "Category": "WASHING MACHINES", "Brand": "SAMSUNG", "Model": "9KG FRONT LOAD WASHING MACHINE QUICKDRIVE\u2122 WW90T754DWH/SP (WHITE)", "Discounted Price": 1281.0, "Listed Price": 1281.0, "Discount Percentage": 0, "Date Collected": "29/02/2024"},
{"Platform": "COURTS", "Category": "WASHING MACHINES", "Brand": "HITACHI", "Model": "16KG TOP LOAD WASHING MACHINE SF160ZCV", "Discounted Price": 1299.0, "Listed Price": 1599.0, "Discount Percentage": 18.76, "Date Collected": "29/02/2024"},
{"Platform": "COURTS", "Category": "WASHING MACHINES", "Brand": "LG", "Model": "13KG SMART INVERTER TOP LOAD WASHING MACHINE TURBOWASH3D\u2122 TH2113SSAK (BLACK STEEL)", "Discounted Price": 1299.0, "Listed Price": 1721.0, "Discount Percentage": 24.52, "Date Collected": "29/02/2024"},
{"Platform": "COURTS", "Category": "WASHING MACHINES", "Brand": "SHARP", "Model": "10.5KG FRONT LOAD WASHING MACHINE ES-FW105SG", "Discounted Price": 1311.0, "Listed Price": 1395.0, "Discount Percentage": 6.02, "Date Collected": "29/02/2024"},
{"Platform": "COURTS", "Category": "WASHING MACHINES", "Brand": "SAMSUNG", "Model": "8.5KG FRONT LOAD WASHING MACHINE QUICKDRIVE\u2122 WW85T954DSH/SP (WHITE)", "Discounted Price": 1323.0, "Listed Price": 1323.0, "Discount Percentage": 0, "Date Collected": "29/02/2024"},
{"Platform": "COURTS", "Category": "WASHING MACHINES", "Brand": "HITACHI", "Model": "9KG FRONT LOAD WASHING MACHINE BDW90AVWH", "Discounted Price": 1323.0, "Listed Price": 1833.0, "Discount Percentage": 27.82, "Date Collected": "29/02/2024"},
{"Platform": "COURTS", "Category": "WASHING MACHINES", "Brand": "LG", "Model": "9KG FRONT LOAD WASHING MACHINE AI DIRECTDRIVE\u2122 FV1409S3W (WHITE)", "Discounted Price": 1324.0, "Listed Price": 2088.0, "Discount Percentage": 36.59, "Date Collected": "29/02/2024"},
{"Platform": "COURTS", "Category": "WASHING MACHINES", "Brand": "LG", "Model": "9KG FRONT LOAD WASHING MACHINE AI DIRECTDRIVE\u2122 FV1409S3W (WHITE)", "Discounted Price": 1324.0, "Listed Price": 2088.0, "Discount Percentage": 36.59, "Date Collected": "29/02/2024"},
{"Platform": "COURTS", "Category": "WASHING MACHINES", "Brand": "BEKO", "Model": "10KG FREESTANDING FRONT LOAD WASHING MACHINE WTE10744X0D (WHITE)", "Discounted Price": 1329.0, "Listed Price": 1499.0, "Discount Percentage": 11.34, "Date Collected": "29/02/2024"},
{"Platform": "COURTS", "Category": "WASHING MACHINES", "Brand": "BEKO", "Model": "12KG FRONT LOAD WASHER WTE12746X0 (WHITE)", "Discounted Price": 1389.0, "Listed Price": 1499.0, "Discount Percentage": 7.34, "Date Collected": "29/02/2024"},
{"Platform": "COURTS", "Category": "WASHING MACHINES", "Brand": "SAMSUNG", "Model": "9.5KG BESPOKE FRONTLOAD WASHER WW95BB944DGBSP (BLACK)", "Discounted Price": 1513.0, "Listed Price": 1513.0, "Discount Percentage": 0, "Date Collected": "29/02/2024"},
{"Platform": "COURTS", "Category": "WASHING MACHINES", "Brand": "SAMSUNG", "Model": "10.5KG FRONT LOAD WASHING MACHINE WW10T754DBX/SP", "Discounted Price": 1578.0, "Listed Price": 1578.0, "Discount Percentage": 0, "Date Collected": "29/02/2024"},
{"Platform": "COURTS", "Category": "WASHING MACHINES", "Brand": "SAMSUNG", "Model": "9.5KG FRONT LOAD WASHING MACHINE QUICKDRIVE\u2122 WW95T984DSH/SP (WHITE)", "Discounted Price": 1584.0, "Listed Price": 1584.0, "Discount Percentage": 0, "Date Collected": "29/02/2024"},
{"Platform": "COURTS", "Category": "WASHING MACHINES", "Brand": "HITACHI", "Model": "10KG FRONT LOADING WASHER AI WASH BD-100GV (WHITE)", "Discounted Price": 1619.0, "Listed Price": 2199.0, "Discount Percentage": 26.38, "Date Collected": "29/02/2024"},
{"Platform": "COURTS", "Category": "WASHING MACHINES", "Brand": "WHIRLPOOL", "Model": "10.5KG FRONT LOAD WASHER OXYCARE FWMD10502GG", "Discounted Price": 1619.0, "Listed Price": 1619.0, "Discount Percentage": 0, "Date Collected": "29/02/2024"},
{"Platform": "COURTS", "Category": "WASHING MACHINES", "Brand": "SAMSUNG", "Model": "10.5KG FRONT LOAD WASHING MACHINE QUICKDRIVE\u2122 WW10T784DBX/SP (INOX)", "Discounted Price": 1634.0, "Listed Price": 1634.0, "Discount Percentage": 0, "Date Collected": "29/02/2024"},
{"Platform": "COURTS", "Category": "WASHING MACHINES", "Brand": "BOSCH", "Model": "8KG FRONT LOAD WASHING MACHINE WAJ20180SG", "Discounted Price": 1715.0, "Listed Price": 1917.0, "Discount Percentage": 10.54, "Date Collected": "29/02/2024"},
{"Platform": "COURTS", "Category": "WASHING MACHINES", "Brand": "SAMSUNG", "Model": "10.5KG/7KG FRONT LOAD WASHER DRYER COMBO QUICKDRIVE\u2122 WD10T784DBX/SP (INOX)", "Discounted Price": 1836.0, "Listed Price": 1836.0, "Discount Percentage": 0, "Date Collected": "29/02/2024"},
{"Platform": "COURTS", "Category": "WASHING MACHINES", "Brand": "SAMSUNG", "Model": "WW12BB944DGBSP BESPOKE FRONTLOAD WASHER (12KG)", "Discounted Price": 1967.0, "Listed Price": 1967.0, "Discount Percentage": 0, "Date Collected": "29/02/2024"},
{"Platform": "COURTS", "Category": "WASHING MACHINES", "Brand": "SAMSUNG", "Model": "21KG/12KG FRONT LOAD WASHER DRYER WD21B6400KV/SP (BLACK)", "Discounted Price": 2876.0, "Listed Price": 2876.0, "Discount Percentage": 0, "Date Collected": "29/02/2024"},
{"Platform": "COURTS", "Category": "WASHING MACHINES", "Brand": "LG", "Model": "14KG/10KG FRONT LOAD ALL-IN-ONE STACKED WASHER DRYER OBJET WASH TOWER\u2122  WT1410NHEG (GREEN/BEIGE)", "Discounted Price": 4440.0, "Listed Price": 5651.0, "Discount Percentage": 21.43, "Date Collected": "29/02/2024"},
{"Platform": "COURTS", "Category": "WASHING MACHINES", "Brand": "LG", "Model": "WT2116NHEG FRONT LOAD WASH TOWER (21/16KG)", "Discounted Price": 5500.0, "Listed Price": 6937.0, "Discount Percentage": 20.72, "Date Collected": "29/02/2024"},
{"Platform": "COURTS", "Category": "WASHING MACHINES", "Brand": "PANASONIC", "Model": "9KG TOP LOAD WASHING MACHINE STAIN CARE NA-F90A9HRQ (LIGHT GREY)", "Discounted Price": 509.0, "Listed Price": 629.0, "Discount Percentage": 19.08, "Date Collected": "29/02/2024"},
{"Platform": "COURTS", "Category": "WASHING MACHINES", "Brand": "PANASONIC", "Model": "10KG TOP LOAD WASHING MACHINE STAIN CARE NA-F100A9HRQ (LIGHT GREY)", "Discounted Price": 545.0, "Listed Price": 699.0, "Discount Percentage": 22.03, "Date Collected": "29/02/2024"},
{"Platform": "COURTS", "Category": "WASHING MACHINES", "Brand": "TOSHIBA", "Model": "8.5KG FRONT LOAD WASHING MACHINE TW-BL95A4S", "Discounted Price": 599.0, "Listed Price": 749.0, "Discount Percentage": 20.03, "Date Collected": "29/02/2024"},
{"Platform": "COURTS", "Category": "WASHING MACHINES", "Brand": "PANASONIC", "Model": "10KG TOP LOAD WASHING MACHINE STAIN CARE NA-FD10X1HRQ (LIGHT GREY)", "Discounted Price": 629.0, "Listed Price": 879.0, "Discount Percentage": 28.44, "Date Collected": "29/02/2024"},
{"Platform": "COURTS", "Category": "WASHING MACHINES", "Brand": "TOSHIBA", "Model": "12KG TOP LOAD WASHING MACHINE AW-DUM1300KS", "Discounted Price": 745.0, "Listed Price": 899.0, "Discount Percentage": 17.13, "Date Collected": "29/02/2024"},
{"Platform": "COURTS", "Category": "WASHING MACHINES", "Brand": "PANASONIC", "Model": "14KG TOP LOAD WASHING MACHINE FOR SPEICAL STAIN CARE NA-FD14V1BRQ (BLACK SLIVER)", "Discounted Price": 1123.0, "Listed Price": 1439.0, "Discount Percentage": 21.96, "Date Collected": "29/02/2024"},
{"Platform": "COURTS", "Category": "WASHING MACHINES", "Brand": "WHIRLPOOL", "Model": "10.5KG SUPREME OXYCARE FRONT LOAD WASHER  FWMD10502GW", "Discounted Price": 1349.0, "Listed Price": 1519.0, "Discount Percentage": 11.19, "Date Collected": "29/02/2024"},
{"Platform": "COURTS", "Category": "WASHING MACHINES", "Brand": "SHARP", "Model": "ES-FH105BG-W FRONT LOAD WASHER (10.5KG)", "Discounted Price": 899.0, "Listed Price": 956.0, "Discount Percentage": 5.96, "Date Collected": "29/02/2024"},
{"Platform": "COURTS", "Category": "WASHING MACHINES", "Brand": "TOSHIBA", "Model": "TW-T21BU105UWS(MG) FRONT LOAD WASHER (9.5KG)", "Discounted Price": 999.0, "Listed Price": 999.0, "Discount Percentage": 0, "Date Collected": "29/02/2024"},
{"Platform": "COURTS", "Category": "WASHING MACHINES", "Brand": "TOSHIBA", "Model": "TW-T21BU115UWS(MG) FRONT LOAD WASHER (10.5KG)", "Discounted Price": 1099.0, "Listed Price": 1099.0, "Discount Percentage": 0, "Date Collected": "29/02/2024"},
{"Platform": "COURTS", "Category": "WASHING MACHINES", "Brand": "EUROPACE", "Model": "12KG TOP LOAD WASHER ETW 7121Y", "Discounted Price": 709.0, "Listed Price": 899.0, "Discount Percentage": 21.13, "Date Collected": "29/02/2024"},
{"Platform": "COURTS", "Category": "WASHING MACHINES", "Brand": "EUROPACE", "Model": "EFW 9102Y FRONT LOAD WASHER (10KG)", "Discounted Price": 1069.0, "Listed Price": 1499.0, "Discount Percentage": 28.69, "Date Collected": "29/02/2024"},
{"Platform": "COURTS", "Category": "WASHING MACHINES", "Brand": "BOSCH", "Model": "8KG FRONT LOAD WASHER WAN28280SG (WHITE)", "Discounted Price": 1199.0, "Listed Price": 2099.0, "Discount Percentage": 42.88, "Date Collected": "29/02/2024"},
{"Platform": "COURTS", "Category": "WASHING MACHINES", "Brand": "BOSCH", "Model": "9KG FRONT LOAD WASHER WGA14400SG", "Discounted Price": 1699.0, "Listed Price": 2699.0, "Discount Percentage": 37.05, "Date Collected": "29/02/2024"},
{"Platform": "COURTS", "Category": "WASHING MACHINES", "Brand": "WHIRLPOOL", "Model": "10.5KG FRONT LOAD WASHER SUPREME OXYCARE FWMD10512GW", "Discounted Price": 1719.0, "Listed Price": 1899.0, "Discount Percentage": 9.48, "Date Collected": "29/02/2024"},
{"Platform": "COURTS", "Category": "WASHING MACHINES", "Brand": "HITACHI", "Model": "8KG TOP LOAD WASHING MACHINE SF80XB", "Discounted Price": 459.0, "Listed Price": 489.0, "Discount Percentage": 6.13, "Date Collected": "29/02/2024"},
{"Platform": "COURTS", "Category": "WASHING MACHINES", "Brand": "SAMSUNG", "Model": "WA80CG4545BDSP TOP LOAD WASHER -  VERSAILLES GRAY (8KG)", "Discounted Price": 555.0, "Listed Price": 555.0, "Discount Percentage": 0, "Date Collected": "29/02/2024"},
{"Platform": "COURTS", "Category": "WASHING MACHINES", "Brand": "SHARP", "Model": "7KG FRONT LOAD WASHING MACHINE ES-FW70EW", "Discounted Price": 705.0, "Listed Price": 750.0, "Discount Percentage": 6.0, "Date Collected": "29/02/2024"},
{"Platform": "COURTS", "Category": "WASHING MACHINES", "Brand": "SHARP", "Model": "12KG TOP LOAD WASHING MACHINE ES-F120G", "Discounted Price": 756.0, "Listed Price": 804.0, "Discount Percentage": 5.97, "Date Collected": "29/02/2024"},
{"Platform": "COURTS", "Category": "WASHING MACHINES", "Brand": "LG", "Model": "11KG SMART INVERTER TOP LOAD WASHING MACHINE T2311VSAB (BLACK)", "Discounted Price": 763.0, "Listed Price": 1100.0, "Discount Percentage": 30.64, "Date Collected": "29/02/2024"},
{"Platform": "COURTS", "Category": "WASHING MACHINES", "Brand": "HITACHI", "Model": "12KG TOP LOAD WASHING MACHINE SF120XAV", "Discounted Price": 799.0, "Listed Price": 1199.0, "Discount Percentage": 33.36, "Date Collected": "29/02/2024"},
{"Platform": "COURTS", "Category": "WASHING MACHINES", "Brand": "HITACHI", "Model": "10.5KG TOP LOADING WASHER ULTRA-STREAM WASH BW-V105ES (WHITE)", "Discounted Price": 839.0, "Listed Price": 1099.0, "Discount Percentage": 23.66, "Date Collected": "29/02/2024"},
{"Platform": "COURTS", "Category": "WASHING MACHINES", "Brand": "HITACHI", "Model": "14KG TOP LOADING WASHER DYNAMIC-STREAM WASH SF140XA (WHITE)", "Discounted Price": 847.0, "Listed Price": 1109.0, "Discount Percentage": 23.62, "Date Collected": "29/02/2024"},
{"Platform": "COURTS", "Category": "WASHING MACHINES", "Brand": "LG", "Model": "12KG SMART INVERTER TOP LOAD WASHING MACHINE T2312VSAV", "Discounted Price": 865.0, "Listed Price": 1181.0, "Discount Percentage": 26.76, "Date Collected": "29/02/2024"},
{"Platform": "COURTS", "Category": "WASHING MACHINES", "Brand": "LG", "Model": "2.5KG MINI WASHING MACHINE WITH SLIM INVERTER TWINWASH\u2122  TV2425NTWW (WHITE)", "Discounted Price": 886.0, "Listed Price": 998.0, "Discount Percentage": 11.22, "Date Collected": "29/02/2024"},
{"Platform": "COURTS", "Category": "WASHING MACHINES", "Brand": "SAMSUNG", "Model": "11KG TOP LOAD WASHER WA11CG5886BVSP (BLACK CAVIAR)", "Discounted Price": 908.0, "Listed Price": 908.0, "Discount Percentage": 0, "Date Collected": "29/02/2024"},
{"Platform": "COURTS", "Category": "WASHING MACHINES", "Brand": "LG", "Model": "11KG TOP LOAD WASHING MACHINE TURBOWASH3D\u2122 TH2111SSAB (MIDDLE BLACK)", "Discounted Price": 1151.0, "Listed Price": 1436.0, "Discount Percentage": 19.85, "Date Collected": "29/02/2024"},
{"Platform": "COURTS", "Category": "WASHING MACHINES", "Brand": "LG", "Model": "9KG FRONT LOAD WASHING MACHINE AI DIRECTDRIVE\u2122 FV1409S4W (WHITE)", "Discounted Price": 1151.0, "Listed Price": 1813.0, "Discount Percentage": 36.51, "Date Collected": "29/02/2024"},
{"Platform": "COURTS", "Category": "WASHING MACHINES", "Brand": "PANASONIC", "Model": "14KG TOP LOAD WASHING MACHINE STAINMASTER+ WITH DUAL POWER NA-FS14V7SRQ (SUS)", "Discounted Price": 1221.0, "Listed Price": 1375.0, "Discount Percentage": 11.2, "Date Collected": "29/02/2024"},
{"Platform": "COURTS", "Category": "WASHING MACHINES", "Brand": "LG", "Model": "12KG SMART INVERTER TOP LOAD WASHING MACHINE TURBOWASH3D\u2122 TH2112SSAV (SILVER)", "Discounted Price": 1252.0, "Listed Price": 1538.0, "Discount Percentage": 18.6, "Date Collected": "29/02/2024"},
{"Platform": "COURTS", "Category": "WASHING MACHINES", "Brand": "LG", "Model": "13KG SMART INVERTER TOP LOAD WASHING MACHINE TURBOWASH3D\u2122 TH2113SSAK (BLACK STEEL)", "Discounted Price": 1365.0, "Listed Price": 1721.0, "Discount Percentage": 20.69, "Date Collected": "29/02/2024"},
{"Platform": "COURTS", "Category": "WASHING MACHINES", "Brand": "SHARP", "Model": "12.5KG FRONT LOAD WASHER ES-FW125SG", "Discounted Price": 1513.0, "Listed Price": 1610.0, "Discount Percentage": 6.02, "Date Collected": "29/02/2024"},
{"Platform": "COURTS", "Category": "WASHING MACHINES", "Brand": "BOSCH", "Model": "10KG FRONT LOAD WASHER IDOS (WHITE)", "Discounted Price": 4899.0, "Listed Price": 5099.0, "Discount Percentage": 3.92, "Date Collected": "29/02/2024"}
]